{
  "obj": "pattern_36",
  "base_rotation": [
    0.0,
    0.0,
    3.141592653589793
  ],
  "rotation_step": 0.0,
  "fixed_scale": 1000.0,
  "X_MIN": -0.047,
  "X_MAX": -0.01,
  "Y_MIN": -0.072,
  "Y_MAX": -0.01,
  "NUM_OBJ_SAMPLES": 200,
  "OBJ_DEPTH_MIN": 0.001,
  "OBJ_DEPTH_MAX": 0.001,
  "z_anchor": 0.0016526341219703694,
  "valid_cells": [
    {
      "gx": 0,
      "gy": 0,
      "cx": -0.027416,
      "cy": -0.03642,
      "rx": 0.0,
      "ry": 0.0,
      "rz": 3.141593,
      "depth_min": 0.001,
      "depth_max": 0.001,
      "contact_frac": 0.062
    },
    {
      "gx": 1,
      "gy": 0,
      "cx": -0.038547,
      "cy": -0.0406,
      "rx": 0.0,
      "ry": 0.0,
      "rz": 3.141593,
      "depth_min": 0.001,
      "depth_max": 0.001,
      "contact_frac": 0.204
    },
    {
      "gx": 2,
      "gy": 0,
      "cx": -0.041517,
      "cy": -0.022765,
      "rx": 0.0,
      "ry": 0.0,
      "rz": 3.141593,
      "depth_min": 0.001,
      "depth_max": 0.001,
      "contact_frac": 0.098
    },
    {
      "gx": 3,
      "gy": 0,
      "cx": -0.038532,
      "cy": -0.063854,
      "rx": 0.0,
      "ry": 0.0,
      "rz": 3.141593,
      "depth_min": 0.001,
      "depth_max": 0.001,
      "contact_frac": 0.098
    },
    {
      "gx": 4,
      "gy": 0,
      "cx": -0.045015,
      "cy": -0.063134,
      "rx": 0.0,
      "ry": 0.0,
      "rz": 3.141593,
      "depth_min": 0.001,
      "depth_max": 0.001,
      "contact_frac": 0.093
    },
    {
      "gx": 5,
      "gy": 0,
      "cx": -0.045791,
      "cy": -0.031454,
      "rx": 0.0,
      "ry": 0.0,
      "rz": 3.141593,
      "depth_min": 0.001,
      "depth_max": 0.001,
      "contact_frac": 0.058
    },
    {
      "gx": 6,
      "gy": 0,
      "cx": -0.041942,
      "cy": -0.066935,
      "rx": 0.0,
      "ry": 0.0,
      "rz": 3.141593,
      "depth_min": 0.001,
      "depth_max": 0.001,
      "contact_frac": 0.068
    },
    {
      "gx": 7,
      "gy": 0,
      "cx": -0.044035,
      "cy": -0.049442,
      "rx": 0.0,
      "ry": 0.0,
      "rz": 3.141593,
      "depth_min": 0.001,
      "depth_max": 0.001,
      "contact_frac": 0.099
    },
    {
      "gx": 8,
      "gy": 0,
      "cx": -0.042085,
      "cy": -0.016458,
      "rx": 0.0,
      "ry": 0.0,
      "rz": 3.141593,
      "depth_min": 0.001,
      "depth_max": 0.001,
      "contact_frac": 0.097
    },
    {
      "gx": 9,
      "gy": 0,
      "cx": -0.045006,
      "cy": -0.0535,
      "rx": 0.0,
      "ry": 0.0,
      "rz": 3.141593,
      "depth_min": 0.001,
      "depth_max": 0.001,
      "contact_frac": 0.103
    },
    {
      "gx": 10,
      "gy": 0,
      "cx": -0.036781,
      "cy": -0.068899,
      "rx": 0.0,
      "ry": 0.0,
      "rz": 3.141593,
      "depth_min": 0.001,
      "depth_max": 0.001,
      "contact_frac": 0.055
    },
    {
      "gx": 11,
      "gy": 0,
      "cx": -0.033694,
      "cy": -0.042969,
      "rx": 0.0,
      "ry": 0.0,
      "rz": 3.141593,
      "depth_min": 0.001,
      "depth_max": 0.001,
      "contact_frac": 0.1
    },
    {
      "gx": 12,
      "gy": 0,
      "cx": -0.041484,
      "cy": -0.022697,
      "rx": 0.0,
      "ry": 0.0,
      "rz": 3.141593,
      "depth_min": 0.001,
      "depth_max": 0.001,
      "contact_frac": 0.099
    },
    {
      "gx": 13,
      "gy": 0,
      "cx": -0.041008,
      "cy": -0.02984,
      "rx": 0.0,
      "ry": 0.0,
      "rz": 3.141593,
      "depth_min": 0.001,
      "depth_max": 0.001,
      "contact_frac": 0.096
    },
    {
      "gx": 14,
      "gy": 0,
      "cx": -0.024845,
      "cy": -0.045659,
      "rx": 0.0,
      "ry": 0.0,
      "rz": 3.141593,
      "depth_min": 0.001,
      "depth_max": 0.001,
      "contact_frac": 0.065
    },
    {
      "gx": 15,
      "gy": 0,
      "cx": -0.042756,
      "cy": -0.03467,
      "rx": 0.0,
      "ry": 0.0,
      "rz": 3.141593,
      "depth_min": 0.001,
      "depth_max": 0.001,
      "contact_frac": 0.104
    },
    {
      "gx": 16,
      "gy": 0,
      "cx": -0.040749,
      "cy": -0.050189,
      "rx": 0.0,
      "ry": 0.0,
      "rz": 3.141593,
      "depth_min": 0.001,
      "depth_max": 0.001,
      "contact_frac": 0.097
    },
    {
      "gx": 17,
      "gy": 0,
      "cx": -0.03702,
      "cy": -0.026331,
      "rx": 0.0,
      "ry": 0.0,
      "rz": 3.141593,
      "depth_min": 0.001,
      "depth_max": 0.001,
      "contact_frac": 0.105
    },
    {
      "gx": 18,
      "gy": 0,
      "cx": -0.036646,
      "cy": -0.03112,
      "rx": 0.0,
      "ry": 0.0,
      "rz": 3.141593,
      "depth_min": 0.001,
      "depth_max": 0.001,
      "contact_frac": 0.067
    },
    {
      "gx": 19,
      "gy": 0,
      "cx": -0.042661,
      "cy": -0.028534,
      "rx": 0.0,
      "ry": 0.0,
      "rz": 3.141593,
      "depth_min": 0.001,
      "depth_max": 0.001,
      "contact_frac": 0.105
    },
    {
      "gx": 20,
      "gy": 0,
      "cx": -0.046989,
      "cy": -0.028718,
      "rx": 0.0,
      "ry": 0.0,
      "rz": 3.141593,
      "depth_min": 0.001,
      "depth_max": 0.001,
      "contact_frac": 0.07
    },
    {
      "gx": 21,
      "gy": 0,
      "cx": -0.044999,
      "cy": -0.011813,
      "rx": 0.0,
      "ry": 0.0,
      "rz": 3.141593,
      "depth_min": 0.001,
      "depth_max": 0.001,
      "contact_frac": 0.054
    },
    {
      "gx": 22,
      "gy": 0,
      "cx": -0.046054,
      "cy": -0.056053,
      "rx": 0.0,
      "ry": 0.0,
      "rz": 3.141593,
      "depth_min": 0.001,
      "depth_max": 0.001,
      "contact_frac": 0.053
    },
    {
      "gx": 23,
      "gy": 0,
      "cx": -0.040859,
      "cy": -0.024946,
      "rx": 0.0,
      "ry": 0.0,
      "rz": 3.141593,
      "depth_min": 0.001,
      "depth_max": 0.001,
      "contact_frac": 0.098
    },
    {
      "gx": 24,
      "gy": 0,
      "cx": -0.041602,
      "cy": -0.046458,
      "rx": 0.0,
      "ry": 0.0,
      "rz": 3.141593,
      "depth_min": 0.001,
      "depth_max": 0.001,
      "contact_frac": 0.112
    },
    {
      "gx": 25,
      "gy": 0,
      "cx": -0.013336,
      "cy": -0.042605,
      "rx": 0.0,
      "ry": 0.0,
      "rz": 3.141593,
      "depth_min": 0.001,
      "depth_max": 0.001,
      "contact_frac": 0.067
    },
    {
      "gx": 26,
      "gy": 0,
      "cx": -0.011359,
      "cy": -0.038096,
      "rx": 0.0,
      "ry": 0.0,
      "rz": 3.141593,
      "depth_min": 0.001,
      "depth_max": 0.001,
      "contact_frac": 0.056
    },
    {
      "gx": 27,
      "gy": 0,
      "cx": -0.035785,
      "cy": -0.046393,
      "rx": 0.0,
      "ry": 0.0,
      "rz": 3.141593,
      "depth_min": 0.001,
      "depth_max": 0.001,
      "contact_frac": 0.079
    },
    {
      "gx": 28,
      "gy": 0,
      "cx": -0.037575,
      "cy": -0.048282,
      "rx": 0.0,
      "ry": 0.0,
      "rz": 3.141593,
      "depth_min": 0.001,
      "depth_max": 0.001,
      "contact_frac": 0.097
    },
    {
      "gx": 29,
      "gy": 0,
      "cx": -0.045309,
      "cy": -0.030061,
      "rx": 0.0,
      "ry": 0.0,
      "rz": 3.141593,
      "depth_min": 0.001,
      "depth_max": 0.001,
      "contact_frac": 0.078
    },
    {
      "gx": 30,
      "gy": 0,
      "cx": -0.044945,
      "cy": -0.061657,
      "rx": 0.0,
      "ry": 0.0,
      "rz": 3.141593,
      "depth_min": 0.001,
      "depth_max": 0.001,
      "contact_frac": 0.097
    },
    {
      "gx": 31,
      "gy": 0,
      "cx": -0.011125,
      "cy": -0.043916,
      "rx": 0.0,
      "ry": 0.0,
      "rz": 3.141593,
      "depth_min": 0.001,
      "depth_max": 0.001,
      "contact_frac": 0.054
    },
    {
      "gx": 32,
      "gy": 0,
      "cx": -0.03671,
      "cy": -0.067098,
      "rx": 0.0,
      "ry": 0.0,
      "rz": 3.141593,
      "depth_min": 0.001,
      "depth_max": 0.001,
      "contact_frac": 0.061
    },
    {
      "gx": 33,
      "gy": 0,
      "cx": -0.038253,
      "cy": -0.061303,
      "rx": 0.0,
      "ry": 0.0,
      "rz": 3.141593,
      "depth_min": 0.001,
      "depth_max": 0.001,
      "contact_frac": 0.1
    },
    {
      "gx": 34,
      "gy": 0,
      "cx": -0.040068,
      "cy": -0.032078,
      "rx": 0.0,
      "ry": 0.0,
      "rz": 3.141593,
      "depth_min": 0.001,
      "depth_max": 0.001,
      "contact_frac": 0.099
    },
    {
      "gx": 35,
      "gy": 0,
      "cx": -0.036728,
      "cy": -0.050759,
      "rx": 0.0,
      "ry": 0.0,
      "rz": 3.141593,
      "depth_min": 0.001,
      "depth_max": 0.001,
      "contact_frac": 0.067
    },
    {
      "gx": 36,
      "gy": 0,
      "cx": -0.041973,
      "cy": -0.012432,
      "rx": 0.0,
      "ry": 0.0,
      "rz": 3.141593,
      "depth_min": 0.001,
      "depth_max": 0.001,
      "contact_frac": 0.052
    },
    {
      "gx": 37,
      "gy": 0,
      "cx": -0.04416,
      "cy": -0.035493,
      "rx": 0.0,
      "ry": 0.0,
      "rz": 3.141593,
      "depth_min": 0.001,
      "depth_max": 0.001,
      "contact_frac": 0.102
    },
    {
      "gx": 38,
      "gy": 0,
      "cx": -0.02487,
      "cy": -0.041835,
      "rx": 0.0,
      "ry": 0.0,
      "rz": 3.141593,
      "depth_min": 0.001,
      "depth_max": 0.001,
      "contact_frac": 0.094
    },
    {
      "gx": 39,
      "gy": 0,
      "cx": -0.025913,
      "cy": -0.041153,
      "rx": 0.0,
      "ry": 0.0,
      "rz": 3.141593,
      "depth_min": 0.001,
      "depth_max": 0.001,
      "contact_frac": 0.092
    },
    {
      "gx": 40,
      "gy": 0,
      "cx": -0.036688,
      "cy": -0.047501,
      "rx": 0.0,
      "ry": 0.0,
      "rz": 3.141593,
      "depth_min": 0.001,
      "depth_max": 0.001,
      "contact_frac": 0.073
    },
    {
      "gx": 41,
      "gy": 0,
      "cx": -0.042523,
      "cy": -0.031569,
      "rx": 0.0,
      "ry": 0.0,
      "rz": 3.141593,
      "depth_min": 0.001,
      "depth_max": 0.001,
      "contact_frac": 0.101
    },
    {
      "gx": 42,
      "gy": 0,
      "cx": -0.017979,
      "cy": -0.045512,
      "rx": 0.0,
      "ry": 0.0,
      "rz": 3.141593,
      "depth_min": 0.001,
      "depth_max": 0.001,
      "contact_frac": 0.077
    },
    {
      "gx": 43,
      "gy": 0,
      "cx": -0.037001,
      "cy": -0.025378,
      "rx": 0.0,
      "ry": 0.0,
      "rz": 3.141593,
      "depth_min": 0.001,
      "depth_max": 0.001,
      "contact_frac": 0.105
    },
    {
      "gx": 44,
      "gy": 0,
      "cx": -0.043571,
      "cy": -0.01188,
      "rx": 0.0,
      "ry": 0.0,
      "rz": 3.141593,
      "depth_min": 0.001,
      "depth_max": 0.001,
      "contact_frac": 0.052
    },
    {
      "gx": 45,
      "gy": 0,
      "cx": -0.030605,
      "cy": -0.037699,
      "rx": 0.0,
      "ry": 0.0,
      "rz": 3.141593,
      "depth_min": 0.001,
      "depth_max": 0.001,
      "contact_frac": 0.098
    },
    {
      "gx": 46,
      "gy": 0,
      "cx": -0.03911,
      "cy": -0.014548,
      "rx": 0.0,
      "ry": 0.0,
      "rz": 3.141593,
      "depth_min": 0.001,
      "depth_max": 0.001,
      "contact_frac": 0.065
    },
    {
      "gx": 47,
      "gy": 0,
      "cx": -0.036412,
      "cy": -0.064241,
      "rx": 0.0,
      "ry": 0.0,
      "rz": 3.141593,
      "depth_min": 0.001,
      "depth_max": 0.001,
      "contact_frac": 0.065
    },
    {
      "gx": 48,
      "gy": 0,
      "cx": -0.03938,
      "cy": -0.034921,
      "rx": 0.0,
      "ry": 0.0,
      "rz": 3.141593,
      "depth_min": 0.001,
      "depth_max": 0.001,
      "contact_frac": 0.108
    },
    {
      "gx": 49,
      "gy": 0,
      "cx": -0.040289,
      "cy": -0.070154,
      "rx": 0.0,
      "ry": 0.0,
      "rz": 3.141593,
      "depth_min": 0.001,
      "depth_max": 0.001,
      "contact_frac": 0.05
    },
    {
      "gx": 50,
      "gy": 0,
      "cx": -0.045286,
      "cy": -0.012824,
      "rx": 0.0,
      "ry": 0.0,
      "rz": 3.141593,
      "depth_min": 0.001,
      "depth_max": 0.001,
      "contact_frac": 0.051
    },
    {
      "gx": 51,
      "gy": 0,
      "cx": -0.03762,
      "cy": -0.03227,
      "rx": 0.0,
      "ry": 0.0,
      "rz": 3.141593,
      "depth_min": 0.001,
      "depth_max": 0.001,
      "contact_frac": 0.094
    },
    {
      "gx": 52,
      "gy": 0,
      "cx": -0.031257,
      "cy": -0.038146,
      "rx": 0.0,
      "ry": 0.0,
      "rz": 3.141593,
      "depth_min": 0.001,
      "depth_max": 0.001,
      "contact_frac": 0.092
    },
    {
      "gx": 53,
      "gy": 0,
      "cx": -0.016838,
      "cy": -0.044367,
      "rx": 0.0,
      "ry": 0.0,
      "rz": 3.141593,
      "depth_min": 0.001,
      "depth_max": 0.001,
      "contact_frac": 0.1
    },
    {
      "gx": 54,
      "gy": 0,
      "cx": -0.036891,
      "cy": -0.05046,
      "rx": 0.0,
      "ry": 0.0,
      "rz": 3.141593,
      "depth_min": 0.001,
      "depth_max": 0.001,
      "contact_frac": 0.078
    },
    {
      "gx": 55,
      "gy": 0,
      "cx": -0.013112,
      "cy": -0.04552,
      "rx": 0.0,
      "ry": 0.0,
      "rz": 3.141593,
      "depth_min": 0.001,
      "depth_max": 0.001,
      "contact_frac": 0.052
    },
    {
      "gx": 56,
      "gy": 0,
      "cx": -0.036836,
      "cy": -0.052459,
      "rx": 0.0,
      "ry": 0.0,
      "rz": 3.141593,
      "depth_min": 0.001,
      "depth_max": 0.001,
      "contact_frac": 0.086
    },
    {
      "gx": 57,
      "gy": 0,
      "cx": -0.044188,
      "cy": -0.034407,
      "rx": 0.0,
      "ry": 0.0,
      "rz": 3.141593,
      "depth_min": 0.001,
      "depth_max": 0.001,
      "contact_frac": 0.105
    },
    {
      "gx": 58,
      "gy": 0,
      "cx": -0.040448,
      "cy": -0.060974,
      "rx": 0.0,
      "ry": 0.0,
      "rz": 3.141593,
      "depth_min": 0.001,
      "depth_max": 0.001,
      "contact_frac": 0.096
    },
    {
      "gx": 59,
      "gy": 0,
      "cx": -0.011886,
      "cy": -0.038783,
      "rx": 0.0,
      "ry": 0.0,
      "rz": 3.141593,
      "depth_min": 0.001,
      "depth_max": 0.001,
      "contact_frac": 0.06
    },
    {
      "gx": 60,
      "gy": 0,
      "cx": -0.045163,
      "cy": -0.033368,
      "rx": 0.0,
      "ry": 0.0,
      "rz": 3.141593,
      "depth_min": 0.001,
      "depth_max": 0.001,
      "contact_frac": 0.085
    },
    {
      "gx": 61,
      "gy": 0,
      "cx": -0.03373,
      "cy": -0.036215,
      "rx": 0.0,
      "ry": 0.0,
      "rz": 3.141593,
      "depth_min": 0.001,
      "depth_max": 0.001,
      "contact_frac": 0.054
    },
    {
      "gx": 62,
      "gy": 0,
      "cx": -0.038822,
      "cy": -0.067971,
      "rx": 0.0,
      "ry": 0.0,
      "rz": 3.141593,
      "depth_min": 0.001,
      "depth_max": 0.001,
      "contact_frac": 0.065
    },
    {
      "gx": 63,
      "gy": 0,
      "cx": -0.038609,
      "cy": -0.061203,
      "rx": 0.0,
      "ry": 0.0,
      "rz": 3.141593,
      "depth_min": 0.001,
      "depth_max": 0.001,
      "contact_frac": 0.099
    },
    {
      "gx": 64,
      "gy": 0,
      "cx": -0.026498,
      "cy": -0.039071,
      "rx": 0.0,
      "ry": 0.0,
      "rz": 3.141593,
      "depth_min": 0.001,
      "depth_max": 0.001,
      "contact_frac": 0.096
    },
    {
      "gx": 65,
      "gy": 0,
      "cx": -0.045939,
      "cy": -0.061258,
      "rx": 0.0,
      "ry": 0.0,
      "rz": 3.141593,
      "depth_min": 0.001,
      "depth_max": 0.001,
      "contact_frac": 0.051
    },
    {
      "gx": 66,
      "gy": 0,
      "cx": -0.041203,
      "cy": -0.024895,
      "rx": 0.0,
      "ry": 0.0,
      "rz": 3.141593,
      "depth_min": 0.001,
      "depth_max": 0.001,
      "contact_frac": 0.099
    },
    {
      "gx": 67,
      "gy": 0,
      "cx": -0.036855,
      "cy": -0.035164,
      "rx": 0.0,
      "ry": 0.0,
      "rz": 3.141593,
      "depth_min": 0.001,
      "depth_max": 0.001,
      "contact_frac": 0.099
    },
    {
      "gx": 68,
      "gy": 0,
      "cx": -0.040814,
      "cy": -0.025586,
      "rx": 0.0,
      "ry": 0.0,
      "rz": 3.141593,
      "depth_min": 0.001,
      "depth_max": 0.001,
      "contact_frac": 0.101
    },
    {
      "gx": 69,
      "gy": 0,
      "cx": -0.025256,
      "cy": -0.045486,
      "rx": 0.0,
      "ry": 0.0,
      "rz": 3.141593,
      "depth_min": 0.001,
      "depth_max": 0.001,
      "contact_frac": 0.07
    },
    {
      "gx": 70,
      "gy": 0,
      "cx": -0.033976,
      "cy": -0.042127,
      "rx": 0.0,
      "ry": 0.0,
      "rz": 3.141593,
      "depth_min": 0.001,
      "depth_max": 0.001,
      "contact_frac": 0.102
    },
    {
      "gx": 71,
      "gy": 0,
      "cx": -0.012974,
      "cy": -0.039581,
      "rx": 0.0,
      "ry": 0.0,
      "rz": 3.141593,
      "depth_min": 0.001,
      "depth_max": 0.001,
      "contact_frac": 0.064
    },
    {
      "gx": 72,
      "gy": 0,
      "cx": -0.039858,
      "cy": -0.049265,
      "rx": 0.0,
      "ry": 0.0,
      "rz": 3.141593,
      "depth_min": 0.001,
      "depth_max": 0.001,
      "contact_frac": 0.097
    },
    {
      "gx": 73,
      "gy": 0,
      "cx": -0.039537,
      "cy": -0.031298,
      "rx": 0.0,
      "ry": 0.0,
      "rz": 3.141593,
      "depth_min": 0.001,
      "depth_max": 0.001,
      "contact_frac": 0.096
    },
    {
      "gx": 74,
      "gy": 0,
      "cx": -0.038527,
      "cy": -0.034866,
      "rx": 0.0,
      "ry": 0.0,
      "rz": 3.141593,
      "depth_min": 0.001,
      "depth_max": 0.001,
      "contact_frac": 0.106
    },
    {
      "gx": 75,
      "gy": 0,
      "cx": -0.037881,
      "cy": -0.059029,
      "rx": 0.0,
      "ry": 0.0,
      "rz": 3.141593,
      "depth_min": 0.001,
      "depth_max": 0.001,
      "contact_frac": 0.103
    },
    {
      "gx": 76,
      "gy": 0,
      "cx": -0.044337,
      "cy": -0.055434,
      "rx": 0.0,
      "ry": 0.0,
      "rz": 3.141593,
      "depth_min": 0.001,
      "depth_max": 0.001,
      "contact_frac": 0.104
    },
    {
      "gx": 77,
      "gy": 0,
      "cx": -0.026771,
      "cy": -0.038497,
      "rx": 0.0,
      "ry": 0.0,
      "rz": 3.141593,
      "depth_min": 0.001,
      "depth_max": 0.001,
      "contact_frac": 0.098
    },
    {
      "gx": 78,
      "gy": 0,
      "cx": -0.01904,
      "cy": -0.041609,
      "rx": 0.0,
      "ry": 0.0,
      "rz": 3.141593,
      "depth_min": 0.001,
      "depth_max": 0.001,
      "contact_frac": 0.102
    },
    {
      "gx": 79,
      "gy": 0,
      "cx": -0.014406,
      "cy": -0.043923,
      "rx": 0.0,
      "ry": 0.0,
      "rz": 3.141593,
      "depth_min": 0.001,
      "depth_max": 0.001,
      "contact_frac": 0.078
    },
    {
      "gx": 80,
      "gy": 0,
      "cx": -0.020224,
      "cy": -0.039798,
      "rx": 0.0,
      "ry": 0.0,
      "rz": 3.141593,
      "depth_min": 0.001,
      "depth_max": 0.001,
      "contact_frac": 0.099
    },
    {
      "gx": 81,
      "gy": 0,
      "cx": -0.04669,
      "cy": -0.016942,
      "rx": 0.0,
      "ry": 0.0,
      "rz": 3.141593,
      "depth_min": 0.001,
      "depth_max": 0.001,
      "contact_frac": 0.053
    },
    {
      "gx": 82,
      "gy": 0,
      "cx": -0.043855,
      "cy": -0.015859,
      "rx": 0.0,
      "ry": 0.0,
      "rz": 3.141593,
      "depth_min": 0.001,
      "depth_max": 0.001,
      "contact_frac": 0.077
    },
    {
      "gx": 83,
      "gy": 0,
      "cx": -0.036957,
      "cy": -0.032265,
      "rx": 0.0,
      "ry": 0.0,
      "rz": 3.141593,
      "depth_min": 0.001,
      "depth_max": 0.001,
      "contact_frac": 0.086
    },
    {
      "gx": 84,
      "gy": 0,
      "cx": -0.03942,
      "cy": -0.060849,
      "rx": 0.0,
      "ry": 0.0,
      "rz": 3.141593,
      "depth_min": 0.001,
      "depth_max": 0.001,
      "contact_frac": 0.097
    },
    {
      "gx": 85,
      "gy": 0,
      "cx": -0.038235,
      "cy": -0.046949,
      "rx": 0.0,
      "ry": 0.0,
      "rz": 3.141593,
      "depth_min": 0.001,
      "depth_max": 0.001,
      "contact_frac": 0.11
    },
    {
      "gx": 86,
      "gy": 0,
      "cx": -0.036671,
      "cy": -0.030664,
      "rx": 0.0,
      "ry": 0.0,
      "rz": 3.141593,
      "depth_min": 0.001,
      "depth_max": 0.001,
      "contact_frac": 0.077
    },
    {
      "gx": 87,
      "gy": 0,
      "cx": -0.0377,
      "cy": -0.039894,
      "rx": 0.0,
      "ry": 0.0,
      "rz": 3.141593,
      "depth_min": 0.001,
      "depth_max": 0.001,
      "contact_frac": 0.203
    },
    {
      "gx": 88,
      "gy": 0,
      "cx": -0.040704,
      "cy": -0.055156,
      "rx": 0.0,
      "ry": 0.0,
      "rz": 3.141593,
      "depth_min": 0.001,
      "depth_max": 0.001,
      "contact_frac": 0.098
    },
    {
      "gx": 89,
      "gy": 0,
      "cx": -0.032908,
      "cy": -0.036625,
      "rx": 0.0,
      "ry": 0.0,
      "rz": 3.141593,
      "depth_min": 0.001,
      "depth_max": 0.001,
      "contact_frac": 0.066
    },
    {
      "gx": 90,
      "gy": 0,
      "cx": -0.020316,
      "cy": -0.04028,
      "rx": 0.0,
      "ry": 0.0,
      "rz": 3.141593,
      "depth_min": 0.001,
      "depth_max": 0.001,
      "contact_frac": 0.095
    },
    {
      "gx": 91,
      "gy": 0,
      "cx": -0.037638,
      "cy": -0.013268,
      "rx": 0.0,
      "ry": 0.0,
      "rz": 3.141593,
      "depth_min": 0.001,
      "depth_max": 0.001,
      "contact_frac": 0.06
    },
    {
      "gx": 92,
      "gy": 0,
      "cx": -0.029486,
      "cy": -0.045611,
      "rx": 0.0,
      "ry": 0.0,
      "rz": 3.141593,
      "depth_min": 0.001,
      "depth_max": 0.001,
      "contact_frac": 0.062
    },
    {
      "gx": 93,
      "gy": 0,
      "cx": -0.01278,
      "cy": -0.045201,
      "rx": 0.0,
      "ry": 0.0,
      "rz": 3.141593,
      "depth_min": 0.001,
      "depth_max": 0.001,
      "contact_frac": 0.057
    },
    {
      "gx": 94,
      "gy": 0,
      "cx": -0.041102,
      "cy": -0.048353,
      "rx": 0.0,
      "ry": 0.0,
      "rz": 3.141593,
      "depth_min": 0.001,
      "depth_max": 0.001,
      "contact_frac": 0.096
    },
    {
      "gx": 95,
      "gy": 0,
      "cx": -0.03175,
      "cy": -0.044662,
      "rx": 0.0,
      "ry": 0.0,
      "rz": 3.141593,
      "depth_min": 0.001,
      "depth_max": 0.001,
      "contact_frac": 0.088
    },
    {
      "gx": 96,
      "gy": 0,
      "cx": -0.037894,
      "cy": -0.029185,
      "rx": 0.0,
      "ry": 0.0,
      "rz": 3.141593,
      "depth_min": 0.001,
      "depth_max": 0.001,
      "contact_frac": 0.104
    },
    {
      "gx": 97,
      "gy": 0,
      "cx": -0.037977,
      "cy": -0.060961,
      "rx": 0.0,
      "ry": 0.0,
      "rz": 3.141593,
      "depth_min": 0.001,
      "depth_max": 0.001,
      "contact_frac": 0.099
    },
    {
      "gx": 98,
      "gy": 0,
      "cx": -0.046965,
      "cy": -0.029992,
      "rx": 0.0,
      "ry": 0.0,
      "rz": 3.141593,
      "depth_min": 0.001,
      "depth_max": 0.001,
      "contact_frac": 0.069
    },
    {
      "gx": 99,
      "gy": 0,
      "cx": -0.036293,
      "cy": -0.030329,
      "rx": 0.0,
      "ry": 0.0,
      "rz": 3.141593,
      "depth_min": 0.001,
      "depth_max": 0.001,
      "contact_frac": 0.061
    },
    {
      "gx": 100,
      "gy": 0,
      "cx": -0.042524,
      "cy": -0.035577,
      "rx": 0.0,
      "ry": 0.0,
      "rz": 3.141593,
      "depth_min": 0.001,
      "depth_max": 0.001,
      "contact_frac": 0.107
    },
    {
      "gx": 101,
      "gy": 0,
      "cx": -0.039498,
      "cy": -0.033758,
      "rx": 0.0,
      "ry": 0.0,
      "rz": 3.141593,
      "depth_min": 0.001,
      "depth_max": 0.001,
      "contact_frac": 0.106
    },
    {
      "gx": 102,
      "gy": 0,
      "cx": -0.031803,
      "cy": -0.038405,
      "rx": 0.0,
      "ry": 0.0,
      "rz": 3.141593,
      "depth_min": 0.001,
      "depth_max": 0.001,
      "contact_frac": 0.092
    },
    {
      "gx": 103,
      "gy": 0,
      "cx": -0.037759,
      "cy": -0.045334,
      "rx": 0.0,
      "ry": 0.0,
      "rz": 3.141593,
      "depth_min": 0.001,
      "depth_max": 0.001,
      "contact_frac": 0.159
    },
    {
      "gx": 104,
      "gy": 0,
      "cx": -0.033082,
      "cy": -0.039399,
      "rx": 0.0,
      "ry": 0.0,
      "rz": 3.141593,
      "depth_min": 0.001,
      "depth_max": 0.001,
      "contact_frac": 0.1
    },
    {
      "gx": 105,
      "gy": 0,
      "cx": -0.029762,
      "cy": -0.036568,
      "rx": 0.0,
      "ry": 0.0,
      "rz": 3.141593,
      "depth_min": 0.001,
      "depth_max": 0.001,
      "contact_frac": 0.066
    },
    {
      "gx": 106,
      "gy": 0,
      "cx": -0.016662,
      "cy": -0.040955,
      "rx": 0.0,
      "ry": 0.0,
      "rz": 3.141593,
      "depth_min": 0.001,
      "depth_max": 0.001,
      "contact_frac": 0.094
    },
    {
      "gx": 107,
      "gy": 0,
      "cx": -0.029681,
      "cy": -0.041847,
      "rx": 0.0,
      "ry": 0.0,
      "rz": 3.141593,
      "depth_min": 0.001,
      "depth_max": 0.001,
      "contact_frac": 0.092
    },
    {
      "gx": 108,
      "gy": 0,
      "cx": -0.044809,
      "cy": -0.012402,
      "rx": 0.0,
      "ry": 0.0,
      "rz": 3.141593,
      "depth_min": 0.001,
      "depth_max": 0.001,
      "contact_frac": 0.058
    },
    {
      "gx": 109,
      "gy": 0,
      "cx": -0.036202,
      "cy": -0.021352,
      "rx": 0.0,
      "ry": 0.0,
      "rz": 3.141593,
      "depth_min": 0.001,
      "depth_max": 0.001,
      "contact_frac": 0.058
    },
    {
      "gx": 110,
      "gy": 0,
      "cx": -0.033775,
      "cy": -0.044116,
      "rx": 0.0,
      "ry": 0.0,
      "rz": 3.141593,
      "depth_min": 0.001,
      "depth_max": 0.001,
      "contact_frac": 0.098
    },
    {
      "gx": 111,
      "gy": 0,
      "cx": -0.019759,
      "cy": -0.044767,
      "rx": 0.0,
      "ry": 0.0,
      "rz": 3.141593,
      "depth_min": 0.001,
      "depth_max": 0.001,
      "contact_frac": 0.101
    },
    {
      "gx": 112,
      "gy": 0,
      "cx": -0.038209,
      "cy": -0.036295,
      "rx": 0.0,
      "ry": 0.0,
      "rz": 3.141593,
      "depth_min": 0.001,
      "depth_max": 0.001,
      "contact_frac": 0.146
    },
    {
      "gx": 113,
      "gy": 0,
      "cx": -0.028571,
      "cy": -0.041045,
      "rx": 0.0,
      "ry": 0.0,
      "rz": 3.141593,
      "depth_min": 0.001,
      "depth_max": 0.001,
      "contact_frac": 0.091
    },
    {
      "gx": 114,
      "gy": 0,
      "cx": -0.037122,
      "cy": -0.029122,
      "rx": 0.0,
      "ry": 0.0,
      "rz": 3.141593,
      "depth_min": 0.001,
      "depth_max": 0.001,
      "contact_frac": 0.104
    },
    {
      "gx": 115,
      "gy": 0,
      "cx": -0.037865,
      "cy": -0.019559,
      "rx": 0.0,
      "ry": 0.0,
      "rz": 3.141593,
      "depth_min": 0.001,
      "depth_max": 0.001,
      "contact_frac": 0.101
    },
    {
      "gx": 116,
      "gy": 0,
      "cx": -0.036828,
      "cy": -0.03361,
      "rx": 0.0,
      "ry": 0.0,
      "rz": 3.141593,
      "depth_min": 0.001,
      "depth_max": 0.001,
      "contact_frac": 0.084
    },
    {
      "gx": 117,
      "gy": 0,
      "cx": -0.041159,
      "cy": -0.056593,
      "rx": 0.0,
      "ry": 0.0,
      "rz": 3.141593,
      "depth_min": 0.001,
      "depth_max": 0.001,
      "contact_frac": 0.096
    },
    {
      "gx": 118,
      "gy": 0,
      "cx": -0.036374,
      "cy": -0.046761,
      "rx": 0.0,
      "ry": 0.0,
      "rz": 3.141593,
      "depth_min": 0.001,
      "depth_max": 0.001,
      "contact_frac": 0.084
    },
    {
      "gx": 119,
      "gy": 0,
      "cx": -0.043377,
      "cy": -0.039278,
      "rx": 0.0,
      "ry": 0.0,
      "rz": 3.141593,
      "depth_min": 0.001,
      "depth_max": 0.001,
      "contact_frac": 0.115
    },
    {
      "gx": 120,
      "gy": 0,
      "cx": -0.041797,
      "cy": -0.038747,
      "rx": 0.0,
      "ry": 0.0,
      "rz": 3.141593,
      "depth_min": 0.001,
      "depth_max": 0.001,
      "contact_frac": 0.129
    },
    {
      "gx": 121,
      "gy": 0,
      "cx": -0.011872,
      "cy": -0.039491,
      "rx": 0.0,
      "ry": 0.0,
      "rz": 3.141593,
      "depth_min": 0.001,
      "depth_max": 0.001,
      "contact_frac": 0.058
    },
    {
      "gx": 122,
      "gy": 0,
      "cx": -0.042917,
      "cy": -0.037204,
      "rx": 0.0,
      "ry": 0.0,
      "rz": 3.141593,
      "depth_min": 0.001,
      "depth_max": 0.001,
      "contact_frac": 0.119
    },
    {
      "gx": 123,
      "gy": 0,
      "cx": -0.040844,
      "cy": -0.065647,
      "rx": 0.0,
      "ry": 0.0,
      "rz": 3.141593,
      "depth_min": 0.001,
      "depth_max": 0.001,
      "contact_frac": 0.088
    },
    {
      "gx": 124,
      "gy": 0,
      "cx": -0.044323,
      "cy": -0.051391,
      "rx": 0.0,
      "ry": 0.0,
      "rz": 3.141593,
      "depth_min": 0.001,
      "depth_max": 0.001,
      "contact_frac": 0.102
    },
    {
      "gx": 125,
      "gy": 0,
      "cx": -0.044432,
      "cy": -0.029214,
      "rx": 0.0,
      "ry": 0.0,
      "rz": 3.141593,
      "depth_min": 0.001,
      "depth_max": 0.001,
      "contact_frac": 0.107
    },
    {
      "gx": 126,
      "gy": 0,
      "cx": -0.027433,
      "cy": -0.042116,
      "rx": 0.0,
      "ry": 0.0,
      "rz": 3.141593,
      "depth_min": 0.001,
      "depth_max": 0.001,
      "contact_frac": 0.094
    },
    {
      "gx": 127,
      "gy": 0,
      "cx": -0.039092,
      "cy": -0.026267,
      "rx": 0.0,
      "ry": 0.0,
      "rz": 3.141593,
      "depth_min": 0.001,
      "depth_max": 0.001,
      "contact_frac": 0.105
    },
    {
      "gx": 128,
      "gy": 0,
      "cx": -0.034964,
      "cy": -0.04454,
      "rx": 0.0,
      "ry": 0.0,
      "rz": 3.141593,
      "depth_min": 0.001,
      "depth_max": 0.001,
      "contact_frac": 0.101
    },
    {
      "gx": 129,
      "gy": 0,
      "cx": -0.04082,
      "cy": -0.05573,
      "rx": 0.0,
      "ry": 0.0,
      "rz": 3.141593,
      "depth_min": 0.001,
      "depth_max": 0.001,
      "contact_frac": 0.097
    },
    {
      "gx": 130,
      "gy": 0,
      "cx": -0.044373,
      "cy": -0.051117,
      "rx": 0.0,
      "ry": 0.0,
      "rz": 3.141593,
      "depth_min": 0.001,
      "depth_max": 0.001,
      "contact_frac": 0.103
    },
    {
      "gx": 131,
      "gy": 0,
      "cx": -0.0452,
      "cy": -0.022331,
      "rx": 0.0,
      "ry": 0.0,
      "rz": 3.141593,
      "depth_min": 0.001,
      "depth_max": 0.001,
      "contact_frac": 0.086
    },
    {
      "gx": 132,
      "gy": 0,
      "cx": -0.012015,
      "cy": -0.037647,
      "rx": 0.0,
      "ry": 0.0,
      "rz": 3.141593,
      "depth_min": 0.001,
      "depth_max": 0.001,
      "contact_frac": 0.063
    },
    {
      "gx": 133,
      "gy": 0,
      "cx": -0.045371,
      "cy": -0.034869,
      "rx": 0.0,
      "ry": 0.0,
      "rz": 3.141593,
      "depth_min": 0.001,
      "depth_max": 0.001,
      "contact_frac": 0.076
    },
    {
      "gx": 134,
      "gy": 0,
      "cx": -0.043581,
      "cy": -0.042658,
      "rx": 0.0,
      "ry": 0.0,
      "rz": 3.141593,
      "depth_min": 0.001,
      "depth_max": 0.001,
      "contact_frac": 0.114
    },
    {
      "gx": 135,
      "gy": 0,
      "cx": -0.02481,
      "cy": -0.045683,
      "rx": 0.0,
      "ry": 0.0,
      "rz": 3.141593,
      "depth_min": 0.001,
      "depth_max": 0.001,
      "contact_frac": 0.063
    },
    {
      "gx": 136,
      "gy": 0,
      "cx": -0.024832,
      "cy": -0.036234,
      "rx": 0.0,
      "ry": 0.0,
      "rz": 3.141593,
      "depth_min": 0.001,
      "depth_max": 0.001,
      "contact_frac": 0.053
    },
    {
      "gx": 137,
      "gy": 0,
      "cx": -0.020901,
      "cy": -0.036289,
      "rx": 0.0,
      "ry": 0.0,
      "rz": 3.141593,
      "depth_min": 0.001,
      "depth_max": 0.001,
      "contact_frac": 0.054
    },
    {
      "gx": 138,
      "gy": 0,
      "cx": -0.038555,
      "cy": -0.038859,
      "rx": 0.0,
      "ry": 0.0,
      "rz": 3.141593,
      "depth_min": 0.001,
      "depth_max": 0.001,
      "contact_frac": 0.192
    },
    {
      "gx": 139,
      "gy": 0,
      "cx": -0.027235,
      "cy": -0.044755,
      "rx": 0.0,
      "ry": 0.0,
      "rz": 3.141593,
      "depth_min": 0.001,
      "depth_max": 0.001,
      "contact_frac": 0.098
    },
    {
      "gx": 140,
      "gy": 0,
      "cx": -0.038975,
      "cy": -0.050695,
      "rx": 0.0,
      "ry": 0.0,
      "rz": 3.141593,
      "depth_min": 0.001,
      "depth_max": 0.001,
      "contact_frac": 0.094
    },
    {
      "gx": 141,
      "gy": 0,
      "cx": -0.023889,
      "cy": -0.044962,
      "rx": 0.0,
      "ry": 0.0,
      "rz": 3.141593,
      "depth_min": 0.001,
      "depth_max": 0.001,
      "contact_frac": 0.099
    },
    {
      "gx": 142,
      "gy": 0,
      "cx": -0.024492,
      "cy": -0.039777,
      "rx": 0.0,
      "ry": 0.0,
      "rz": 3.141593,
      "depth_min": 0.001,
      "depth_max": 0.001,
      "contact_frac": 0.094
    },
    {
      "gx": 143,
      "gy": 0,
      "cx": -0.039655,
      "cy": -0.013168,
      "rx": 0.0,
      "ry": 0.0,
      "rz": 3.141593,
      "depth_min": 0.001,
      "depth_max": 0.001,
      "contact_frac": 0.056
    },
    {
      "gx": 144,
      "gy": 0,
      "cx": -0.040906,
      "cy": -0.050731,
      "rx": 0.0,
      "ry": 0.0,
      "rz": 3.141593,
      "depth_min": 0.001,
      "depth_max": 0.001,
      "contact_frac": 0.095
    },
    {
      "gx": 145,
      "gy": 0,
      "cx": -0.030688,
      "cy": -0.045646,
      "rx": 0.0,
      "ry": 0.0,
      "rz": 3.141593,
      "depth_min": 0.001,
      "depth_max": 0.001,
      "contact_frac": 0.062
    },
    {
      "gx": 146,
      "gy": 0,
      "cx": -0.01682,
      "cy": -0.040575,
      "rx": 0.0,
      "ry": 0.0,
      "rz": 3.141593,
      "depth_min": 0.001,
      "depth_max": 0.001,
      "contact_frac": 0.097
    },
    {
      "gx": 147,
      "gy": 0,
      "cx": -0.045329,
      "cy": -0.068379,
      "rx": 0.0,
      "ry": 0.0,
      "rz": 3.141593,
      "depth_min": 0.001,
      "depth_max": 0.001,
      "contact_frac": 0.053
    },
    {
      "gx": 148,
      "gy": 0,
      "cx": -0.040024,
      "cy": -0.016707,
      "rx": 0.0,
      "ry": 0.0,
      "rz": 3.141593,
      "depth_min": 0.001,
      "depth_max": 0.001,
      "contact_frac": 0.094
    },
    {
      "gx": 149,
      "gy": 0,
      "cx": -0.038944,
      "cy": -0.016386,
      "rx": 0.0,
      "ry": 0.0,
      "rz": 3.141593,
      "depth_min": 0.001,
      "depth_max": 0.001,
      "contact_frac": 0.096
    },
    {
      "gx": 150,
      "gy": 0,
      "cx": -0.031178,
      "cy": -0.039403,
      "rx": 0.0,
      "ry": 0.0,
      "rz": 3.141593,
      "depth_min": 0.001,
      "depth_max": 0.001,
      "contact_frac": 0.095
    },
    {
      "gx": 151,
      "gy": 0,
      "cx": -0.037776,
      "cy": -0.043927,
      "rx": 0.0,
      "ry": 0.0,
      "rz": 3.141593,
      "depth_min": 0.001,
      "depth_max": 0.001,
      "contact_frac": 0.186
    },
    {
      "gx": 152,
      "gy": 0,
      "cx": -0.038049,
      "cy": -0.013789,
      "rx": 0.0,
      "ry": 0.0,
      "rz": 3.141593,
      "depth_min": 0.001,
      "depth_max": 0.001,
      "contact_frac": 0.062
    },
    {
      "gx": 153,
      "gy": 0,
      "cx": -0.039082,
      "cy": -0.018321,
      "rx": 0.0,
      "ry": 0.0,
      "rz": 3.141593,
      "depth_min": 0.001,
      "depth_max": 0.001,
      "contact_frac": 0.099
    },
    {
      "gx": 154,
      "gy": 0,
      "cx": -0.03696,
      "cy": -0.061273,
      "rx": 0.0,
      "ry": 0.0,
      "rz": 3.141593,
      "depth_min": 0.001,
      "depth_max": 0.001,
      "contact_frac": 0.093
    },
    {
      "gx": 155,
      "gy": 0,
      "cx": -0.036472,
      "cy": -0.053032,
      "rx": 0.0,
      "ry": 0.0,
      "rz": 3.141593,
      "depth_min": 0.001,
      "depth_max": 0.001,
      "contact_frac": 0.066
    },
    {
      "gx": 156,
      "gy": 0,
      "cx": -0.038066,
      "cy": -0.065443,
      "rx": 0.0,
      "ry": 0.0,
      "rz": 3.141593,
      "depth_min": 0.001,
      "depth_max": 0.001,
      "contact_frac": 0.093
    },
    {
      "gx": 157,
      "gy": 0,
      "cx": -0.02648,
      "cy": -0.04418,
      "rx": 0.0,
      "ry": 0.0,
      "rz": 3.141593,
      "depth_min": 0.001,
      "depth_max": 0.001,
      "contact_frac": 0.099
    },
    {
      "gx": 158,
      "gy": 0,
      "cx": -0.019702,
      "cy": -0.04217,
      "rx": 0.0,
      "ry": 0.0,
      "rz": 3.141593,
      "depth_min": 0.001,
      "depth_max": 0.001,
      "contact_frac": 0.101
    },
    {
      "gx": 159,
      "gy": 0,
      "cx": -0.037821,
      "cy": -0.051954,
      "rx": 0.0,
      "ry": 0.0,
      "rz": 3.141593,
      "depth_min": 0.001,
      "depth_max": 0.001,
      "contact_frac": 0.102
    },
    {
      "gx": 160,
      "gy": 0,
      "cx": -0.021648,
      "cy": -0.03829,
      "rx": 0.0,
      "ry": 0.0,
      "rz": 3.141593,
      "depth_min": 0.001,
      "depth_max": 0.001,
      "contact_frac": 0.098
    },
    {
      "gx": 161,
      "gy": 0,
      "cx": -0.043403,
      "cy": -0.06136,
      "rx": 0.0,
      "ry": 0.0,
      "rz": 3.141593,
      "depth_min": 0.001,
      "depth_max": 0.001,
      "contact_frac": 0.1
    },
    {
      "gx": 162,
      "gy": 0,
      "cx": -0.045746,
      "cy": -0.022041,
      "rx": 0.0,
      "ry": 0.0,
      "rz": 3.141593,
      "depth_min": 0.001,
      "depth_max": 0.001,
      "contact_frac": 0.062
    },
    {
      "gx": 163,
      "gy": 0,
      "cx": -0.017534,
      "cy": -0.046143,
      "rx": 0.0,
      "ry": 0.0,
      "rz": 3.141593,
      "depth_min": 0.001,
      "depth_max": 0.001,
      "contact_frac": 0.053
    },
    {
      "gx": 164,
      "gy": 0,
      "cx": -0.037977,
      "cy": -0.036143,
      "rx": 0.0,
      "ry": 0.0,
      "rz": 3.141593,
      "depth_min": 0.001,
      "depth_max": 0.001,
      "contact_frac": 0.143
    },
    {
      "gx": 165,
      "gy": 0,
      "cx": -0.037145,
      "cy": -0.015236,
      "rx": 0.0,
      "ry": 0.0,
      "rz": 3.141593,
      "depth_min": 0.001,
      "depth_max": 0.001,
      "contact_frac": 0.075
    },
    {
      "gx": 166,
      "gy": 0,
      "cx": -0.046042,
      "cy": -0.025414,
      "rx": 0.0,
      "ry": 0.0,
      "rz": 3.141593,
      "depth_min": 0.001,
      "depth_max": 0.001,
      "contact_frac": 0.053
    },
    {
      "gx": 167,
      "gy": 0,
      "cx": -0.044385,
      "cy": -0.060102,
      "rx": 0.0,
      "ry": 0.0,
      "rz": 3.141593,
      "depth_min": 0.001,
      "depth_max": 0.001,
      "contact_frac": 0.1
    },
    {
      "gx": 168,
      "gy": 0,
      "cx": -0.035213,
      "cy": -0.045601,
      "rx": 0.0,
      "ry": 0.0,
      "rz": 3.141593,
      "depth_min": 0.001,
      "depth_max": 0.001,
      "contact_frac": 0.076
    },
    {
      "gx": 169,
      "gy": 0,
      "cx": -0.045989,
      "cy": -0.04046,
      "rx": 0.0,
      "ry": 0.0,
      "rz": 3.141593,
      "depth_min": 0.001,
      "depth_max": 0.001,
      "contact_frac": 0.052
    },
    {
      "gx": 170,
      "gy": 0,
      "cx": -0.043602,
      "cy": -0.068768,
      "rx": 0.0,
      "ry": 0.0,
      "rz": 3.141593,
      "depth_min": 0.001,
      "depth_max": 0.001,
      "contact_frac": 0.064
    },
    {
      "gx": 171,
      "gy": 0,
      "cx": -0.037032,
      "cy": -0.013315,
      "rx": 0.0,
      "ry": 0.0,
      "rz": 3.141593,
      "depth_min": 0.001,
      "depth_max": 0.001,
      "contact_frac": 0.062
    },
    {
      "gx": 172,
      "gy": 0,
      "cx": -0.040041,
      "cy": -0.039238,
      "rx": 0.0,
      "ry": 0.0,
      "rz": 3.141593,
      "depth_min": 0.001,
      "depth_max": 0.001,
      "contact_frac": 0.185
    },
    {
      "gx": 173,
      "gy": 0,
      "cx": -0.044924,
      "cy": -0.012502,
      "rx": 0.0,
      "ry": 0.0,
      "rz": 3.141593,
      "depth_min": 0.001,
      "depth_max": 0.001,
      "contact_frac": 0.058
    },
    {
      "gx": 174,
      "gy": 0,
      "cx": -0.03665,
      "cy": -0.063853,
      "rx": 0.0,
      "ry": 0.0,
      "rz": 3.141593,
      "depth_min": 0.001,
      "depth_max": 0.001,
      "contact_frac": 0.075
    },
    {
      "gx": 175,
      "gy": 0,
      "cx": -0.017519,
      "cy": -0.043133,
      "rx": 0.0,
      "ry": 0.0,
      "rz": 3.141593,
      "depth_min": 0.001,
      "depth_max": 0.001,
      "contact_frac": 0.103
    },
    {
      "gx": 176,
      "gy": 0,
      "cx": -0.026943,
      "cy": -0.045924,
      "rx": 0.0,
      "ry": 0.0,
      "rz": 3.141593,
      "depth_min": 0.001,
      "depth_max": 0.001,
      "contact_frac": 0.055
    },
    {
      "gx": 177,
      "gy": 0,
      "cx": -0.020362,
      "cy": -0.036748,
      "rx": 0.0,
      "ry": 0.0,
      "rz": 3.141593,
      "depth_min": 0.001,
      "depth_max": 0.001,
      "contact_frac": 0.075
    },
    {
      "gx": 178,
      "gy": 0,
      "cx": -0.019065,
      "cy": -0.039175,
      "rx": 0.0,
      "ry": 0.0,
      "rz": 3.141593,
      "depth_min": 0.001,
      "depth_max": 0.001,
      "contact_frac": 0.105
    },
    {
      "gx": 179,
      "gy": 0,
      "cx": -0.025193,
      "cy": -0.045425,
      "rx": 0.0,
      "ry": 0.0,
      "rz": 3.141593,
      "depth_min": 0.001,
      "depth_max": 0.001,
      "contact_frac": 0.072
    },
    {
      "gx": 180,
      "gy": 0,
      "cx": -0.026708,
      "cy": -0.040611,
      "rx": 0.0,
      "ry": 0.0,
      "rz": 3.141593,
      "depth_min": 0.001,
      "depth_max": 0.001,
      "contact_frac": 0.094
    },
    {
      "gx": 181,
      "gy": 0,
      "cx": -0.025463,
      "cy": -0.045069,
      "rx": 0.0,
      "ry": 0.0,
      "rz": 3.141593,
      "depth_min": 0.001,
      "depth_max": 0.001,
      "contact_frac": 0.089
    },
    {
      "gx": 182,
      "gy": 0,
      "cx": -0.036346,
      "cy": -0.060767,
      "rx": 0.0,
      "ry": 0.0,
      "rz": 3.141593,
      "depth_min": 0.001,
      "depth_max": 0.001,
      "contact_frac": 0.06
    },
    {
      "gx": 183,
      "gy": 0,
      "cx": -0.013916,
      "cy": -0.044097,
      "rx": 0.0,
      "ry": 0.0,
      "rz": 3.141593,
      "depth_min": 0.001,
      "depth_max": 0.001,
      "contact_frac": 0.075
    },
    {
      "gx": 184,
      "gy": 0,
      "cx": -0.04307,
      "cy": -0.042902,
      "rx": 0.0,
      "ry": 0.0,
      "rz": 3.141593,
      "depth_min": 0.001,
      "depth_max": 0.001,
      "contact_frac": 0.119
    },
    {
      "gx": 185,
      "gy": 0,
      "cx": -0.0415,
      "cy": -0.017696,
      "rx": 0.0,
      "ry": 0.0,
      "rz": 3.141593,
      "depth_min": 0.001,
      "depth_max": 0.001,
      "contact_frac": 0.097
    },
    {
      "gx": 186,
      "gy": 0,
      "cx": -0.02664,
      "cy": -0.039752,
      "rx": 0.0,
      "ry": 0.0,
      "rz": 3.141593,
      "depth_min": 0.001,
      "depth_max": 0.001,
      "contact_frac": 0.097
    },
    {
      "gx": 187,
      "gy": 0,
      "cx": -0.032448,
      "cy": -0.039522,
      "rx": 0.0,
      "ry": 0.0,
      "rz": 3.141593,
      "depth_min": 0.001,
      "depth_max": 0.001,
      "contact_frac": 0.097
    },
    {
      "gx": 188,
      "gy": 0,
      "cx": -0.044932,
      "cy": -0.046568,
      "rx": 0.0,
      "ry": 0.0,
      "rz": 3.141593,
      "depth_min": 0.001,
      "depth_max": 0.001,
      "contact_frac": 0.103
    },
    {
      "gx": 189,
      "gy": 0,
      "cx": -0.03704,
      "cy": -0.011821,
      "rx": 0.0,
      "ry": 0.0,
      "rz": 3.141593,
      "depth_min": 0.001,
      "depth_max": 0.001,
      "contact_frac": 0.054
    },
    {
      "gx": 190,
      "gy": 0,
      "cx": -0.044889,
      "cy": -0.059542,
      "rx": 0.0,
      "ry": 0.0,
      "rz": 3.141593,
      "depth_min": 0.001,
      "depth_max": 0.001,
      "contact_frac": 0.101
    },
    {
      "gx": 191,
      "gy": 0,
      "cx": -0.044039,
      "cy": -0.040328,
      "rx": 0.0,
      "ry": 0.0,
      "rz": 3.141593,
      "depth_min": 0.001,
      "depth_max": 0.001,
      "contact_frac": 0.108
    },
    {
      "gx": 192,
      "gy": 0,
      "cx": -0.036551,
      "cy": -0.059734,
      "rx": 0.0,
      "ry": 0.0,
      "rz": 3.141593,
      "depth_min": 0.001,
      "depth_max": 0.001,
      "contact_frac": 0.07
    },
    {
      "gx": 193,
      "gy": 0,
      "cx": -0.041539,
      "cy": -0.045473,
      "rx": 0.0,
      "ry": 0.0,
      "rz": 3.141593,
      "depth_min": 0.001,
      "depth_max": 0.001,
      "contact_frac": 0.123
    },
    {
      "gx": 194,
      "gy": 0,
      "cx": -0.042338,
      "cy": -0.0128,
      "rx": 0.0,
      "ry": 0.0,
      "rz": 3.141593,
      "depth_min": 0.001,
      "depth_max": 0.001,
      "contact_frac": 0.055
    },
    {
      "gx": 195,
      "gy": 0,
      "cx": -0.040409,
      "cy": -0.053956,
      "rx": 0.0,
      "ry": 0.0,
      "rz": 3.141593,
      "depth_min": 0.001,
      "depth_max": 0.001,
      "contact_frac": 0.1
    },
    {
      "gx": 196,
      "gy": 0,
      "cx": -0.037747,
      "cy": -0.022239,
      "rx": 0.0,
      "ry": 0.0,
      "rz": 3.141593,
      "depth_min": 0.001,
      "depth_max": 0.001,
      "contact_frac": 0.1
    },
    {
      "gx": 197,
      "gy": 0,
      "cx": -0.033003,
      "cy": -0.03731,
      "rx": 0.0,
      "ry": 0.0,
      "rz": 3.141593,
      "depth_min": 0.001,
      "depth_max": 0.001,
      "contact_frac": 0.093
    },
    {
      "gx": 198,
      "gy": 0,
      "cx": -0.042157,
      "cy": -0.012506,
      "rx": 0.0,
      "ry": 0.0,
      "rz": 3.141593,
      "depth_min": 0.001,
      "depth_max": 0.001,
      "contact_frac": 0.053
    },
    {
      "gx": 199,
      "gy": 0,
      "cx": -0.026336,
      "cy": -0.037233,
      "rx": 0.0,
      "ry": 0.0,
      "rz": 3.141593,
      "depth_min": 0.001,
      "depth_max": 0.001,
      "contact_frac": 0.095
    }
  ],
  "_rotation_name": "+Z up (original) + Z+180\u00b0",
  "_rotation_degrees": [
    0.0,
    0.0,
    180.0
  ],
  "_sensor_length_mm": 5.0,
  "_sensor_step": 0.006,
  "_target_size_mm": 82.0,
  "_grid": "random-200",
  "_overlap_pct": 40.0,
  "_sampling_method": "random",
  "_use_normal_rotation": false
}