{
  "obj": "peg3",
  "base_rotation": [
    0.0,
    0.0,
    4.71238898038469
  ],
  "rotation_step": 0.0,
  "fixed_scale": 1000.0,
  "X_MIN": 0.01,
  "X_MAX": 0.072,
  "Y_MIN": -0.05104,
  "Y_MAX": -0.03096,
  "NUM_OBJ_SAMPLES": 200,
  "OBJ_DEPTH_MIN": 0.001,
  "OBJ_DEPTH_MAX": 0.001,
  "z_anchor": 0.00649235868,
  "valid_cells": [
    {
      "gx": 0,
      "gy": 0,
      "cx": 0.010871,
      "cy": -0.049674,
      "rx": 0.0,
      "ry": 0.0,
      "rz": 4.712389,
      "depth_min": 0.001,
      "depth_max": 0.001,
      "contact_frac": 0.06
    },
    {
      "gx": 1,
      "gy": 0,
      "cx": 0.047738,
      "cy": -0.049978,
      "rx": 0.0,
      "ry": 0.0,
      "rz": 4.712389,
      "depth_min": 0.001,
      "depth_max": 0.001,
      "contact_frac": 0.085
    },
    {
      "gx": 2,
      "gy": 0,
      "cx": 0.033007,
      "cy": -0.03623,
      "rx": 0.0,
      "ry": 0.0,
      "rz": 4.712389,
      "depth_min": 0.001,
      "depth_max": 0.001,
      "contact_frac": 0.279
    },
    {
      "gx": 3,
      "gy": 0,
      "cx": 0.024212,
      "cy": -0.032628,
      "rx": 0.0,
      "ry": 0.0,
      "rz": 4.712389,
      "depth_min": 0.001,
      "depth_max": 0.001,
      "contact_frac": 0.116
    },
    {
      "gx": 4,
      "gy": 0,
      "cx": 0.032067,
      "cy": -0.035266,
      "rx": 0.0,
      "ry": 0.0,
      "rz": 4.712389,
      "depth_min": 0.001,
      "depth_max": 0.001,
      "contact_frac": 0.234
    },
    {
      "gx": 5,
      "gy": 0,
      "cx": 0.053315,
      "cy": -0.037692,
      "rx": 0.0,
      "ry": 0.0,
      "rz": 4.712389,
      "depth_min": 0.001,
      "depth_max": 0.001,
      "contact_frac": 0.328
    },
    {
      "gx": 6,
      "gy": 0,
      "cx": 0.028655,
      "cy": -0.037791,
      "rx": 0.0,
      "ry": 0.0,
      "rz": 4.712389,
      "depth_min": 0.001,
      "depth_max": 0.001,
      "contact_frac": 0.355
    },
    {
      "gx": 7,
      "gy": 0,
      "cx": 0.034245,
      "cy": -0.048261,
      "rx": 0.0,
      "ry": 0.0,
      "rz": 4.712389,
      "depth_min": 0.001,
      "depth_max": 0.001,
      "contact_frac": 0.161
    },
    {
      "gx": 8,
      "gy": 0,
      "cx": 0.035088,
      "cy": -0.048995,
      "rx": 0.0,
      "ry": 0.0,
      "rz": 4.712389,
      "depth_min": 0.001,
      "depth_max": 0.001,
      "contact_frac": 0.131
    },
    {
      "gx": 9,
      "gy": 0,
      "cx": 0.061531,
      "cy": -0.050043,
      "rx": 0.0,
      "ry": 0.0,
      "rz": 4.712389,
      "depth_min": 0.001,
      "depth_max": 0.001,
      "contact_frac": 0.085
    },
    {
      "gx": 10,
      "gy": 0,
      "cx": 0.020018,
      "cy": -0.035923,
      "rx": 0.0,
      "ry": 0.0,
      "rz": 4.712389,
      "depth_min": 0.001,
      "depth_max": 0.001,
      "contact_frac": 0.231
    },
    {
      "gx": 11,
      "gy": 0,
      "cx": 0.043164,
      "cy": -0.047568,
      "rx": 0.0,
      "ry": 0.0,
      "rz": 4.712389,
      "depth_min": 0.001,
      "depth_max": 0.001,
      "contact_frac": 0.186
    },
    {
      "gx": 12,
      "gy": 0,
      "cx": 0.044422,
      "cy": -0.039336,
      "rx": 0.0,
      "ry": 0.0,
      "rz": 4.712389,
      "depth_min": 0.001,
      "depth_max": 0.001,
      "contact_frac": 0.434
    },
    {
      "gx": 13,
      "gy": 0,
      "cx": 0.054864,
      "cy": -0.039824,
      "rx": 0.0,
      "ry": 0.0,
      "rz": 4.712389,
      "depth_min": 0.001,
      "depth_max": 0.001,
      "contact_frac": 0.46
    },
    {
      "gx": 14,
      "gy": 0,
      "cx": 0.062832,
      "cy": -0.032652,
      "rx": 0.0,
      "ry": 0.0,
      "rz": 4.712389,
      "depth_min": 0.001,
      "depth_max": 0.001,
      "contact_frac": 0.111
    },
    {
      "gx": 15,
      "gy": 0,
      "cx": 0.064309,
      "cy": -0.048969,
      "rx": 0.0,
      "ry": 0.0,
      "rz": 4.712389,
      "depth_min": 0.001,
      "depth_max": 0.001,
      "contact_frac": 0.137
    },
    {
      "gx": 16,
      "gy": 0,
      "cx": 0.020708,
      "cy": -0.038962,
      "rx": 0.0,
      "ry": 0.0,
      "rz": 4.712389,
      "depth_min": 0.001,
      "depth_max": 0.001,
      "contact_frac": 0.4
    },
    {
      "gx": 17,
      "gy": 0,
      "cx": 0.042777,
      "cy": -0.047005,
      "rx": 0.0,
      "ry": 0.0,
      "rz": 4.712389,
      "depth_min": 0.001,
      "depth_max": 0.001,
      "contact_frac": 0.209
    },
    {
      "gx": 18,
      "gy": 0,
      "cx": 0.017334,
      "cy": -0.04898,
      "rx": 0.0,
      "ry": 0.0,
      "rz": 4.712389,
      "depth_min": 0.001,
      "depth_max": 0.001,
      "contact_frac": 0.126
    },
    {
      "gx": 19,
      "gy": 0,
      "cx": 0.062519,
      "cy": -0.032694,
      "rx": 0.0,
      "ry": 0.0,
      "rz": 4.712389,
      "depth_min": 0.001,
      "depth_max": 0.001,
      "contact_frac": 0.112
    },
    {
      "gx": 20,
      "gy": 0,
      "cx": 0.015807,
      "cy": -0.044029,
      "rx": 0.0,
      "ry": 0.0,
      "rz": 4.712389,
      "depth_min": 0.001,
      "depth_max": 0.001,
      "contact_frac": 0.285
    },
    {
      "gx": 21,
      "gy": 0,
      "cx": 0.031246,
      "cy": -0.043684,
      "rx": 0.0,
      "ry": 0.0,
      "rz": 4.712389,
      "depth_min": 0.001,
      "depth_max": 0.001,
      "contact_frac": 0.386
    },
    {
      "gx": 22,
      "gy": 0,
      "cx": 0.040525,
      "cy": -0.0496,
      "rx": 0.0,
      "ry": 0.0,
      "rz": 4.712389,
      "depth_min": 0.001,
      "depth_max": 0.001,
      "contact_frac": 0.113
    },
    {
      "gx": 23,
      "gy": 0,
      "cx": 0.049674,
      "cy": -0.037402,
      "rx": 0.0,
      "ry": 0.0,
      "rz": 4.712389,
      "depth_min": 0.001,
      "depth_max": 0.001,
      "contact_frac": 0.325
    },
    {
      "gx": 24,
      "gy": 0,
      "cx": 0.056895,
      "cy": -0.047577,
      "rx": 0.0,
      "ry": 0.0,
      "rz": 4.712389,
      "depth_min": 0.001,
      "depth_max": 0.001,
      "contact_frac": 0.187
    },
    {
      "gx": 25,
      "gy": 0,
      "cx": 0.040895,
      "cy": -0.033196,
      "rx": 0.0,
      "ry": 0.0,
      "rz": 4.712389,
      "depth_min": 0.001,
      "depth_max": 0.001,
      "contact_frac": 0.132
    },
    {
      "gx": 26,
      "gy": 0,
      "cx": 0.041688,
      "cy": -0.034456,
      "rx": 0.0,
      "ry": 0.0,
      "rz": 4.712389,
      "depth_min": 0.001,
      "depth_max": 0.001,
      "contact_frac": 0.175
    },
    {
      "gx": 27,
      "gy": 0,
      "cx": 0.01022,
      "cy": -0.046868,
      "rx": 0.0,
      "ry": 0.0,
      "rz": 4.712389,
      "depth_min": 0.001,
      "depth_max": 0.001,
      "contact_frac": 0.106
    },
    {
      "gx": 28,
      "gy": 0,
      "cx": 0.051971,
      "cy": -0.050582,
      "rx": 0.0,
      "ry": 0.0,
      "rz": 4.712389,
      "depth_min": 0.001,
      "depth_max": 0.001,
      "contact_frac": 0.063
    },
    {
      "gx": 29,
      "gy": 0,
      "cx": 0.050744,
      "cy": -0.032909,
      "rx": 0.0,
      "ry": 0.0,
      "rz": 4.712389,
      "depth_min": 0.001,
      "depth_max": 0.001,
      "contact_frac": 0.125
    },
    {
      "gx": 30,
      "gy": 0,
      "cx": 0.067845,
      "cy": -0.033622,
      "rx": 0.0,
      "ry": 0.0,
      "rz": 4.712389,
      "depth_min": 0.001,
      "depth_max": 0.001,
      "contact_frac": 0.126
    },
    {
      "gx": 31,
      "gy": 0,
      "cx": 0.039418,
      "cy": -0.049187,
      "rx": 0.0,
      "ry": 0.0,
      "rz": 4.712389,
      "depth_min": 0.001,
      "depth_max": 0.001,
      "contact_frac": 0.126
    },
    {
      "gx": 32,
      "gy": 0,
      "cx": 0.047413,
      "cy": -0.032644,
      "rx": 0.0,
      "ry": 0.0,
      "rz": 4.712389,
      "depth_min": 0.001,
      "depth_max": 0.001,
      "contact_frac": 0.117
    },
    {
      "gx": 33,
      "gy": 0,
      "cx": 0.071013,
      "cy": -0.036753,
      "rx": 0.0,
      "ry": 0.0,
      "rz": 4.712389,
      "depth_min": 0.001,
      "depth_max": 0.001,
      "contact_frac": 0.15
    },
    {
      "gx": 34,
      "gy": 0,
      "cx": 0.033002,
      "cy": -0.042411,
      "rx": 0.0,
      "ry": 0.0,
      "rz": 4.712389,
      "depth_min": 0.001,
      "depth_max": 0.001,
      "contact_frac": 0.473
    },
    {
      "gx": 35,
      "gy": 0,
      "cx": 0.024979,
      "cy": -0.041261,
      "rx": 0.0,
      "ry": 0.0,
      "rz": 4.712389,
      "depth_min": 0.001,
      "depth_max": 0.001,
      "contact_frac": 0.499
    },
    {
      "gx": 36,
      "gy": 0,
      "cx": 0.044093,
      "cy": -0.039835,
      "rx": 0.0,
      "ry": 0.0,
      "rz": 4.712389,
      "depth_min": 0.001,
      "depth_max": 0.001,
      "contact_frac": 0.47
    },
    {
      "gx": 37,
      "gy": 0,
      "cx": 0.056475,
      "cy": -0.048364,
      "rx": 0.0,
      "ry": 0.0,
      "rz": 4.712389,
      "depth_min": 0.001,
      "depth_max": 0.001,
      "contact_frac": 0.149
    },
    {
      "gx": 38,
      "gy": 0,
      "cx": 0.07157,
      "cy": -0.033838,
      "rx": 0.0,
      "ry": 0.0,
      "rz": 4.712389,
      "depth_min": 0.001,
      "depth_max": 0.001,
      "contact_frac": 0.085
    },
    {
      "gx": 39,
      "gy": 0,
      "cx": 0.063056,
      "cy": -0.044817,
      "rx": 0.0,
      "ry": 0.0,
      "rz": 4.712389,
      "depth_min": 0.001,
      "depth_max": 0.001,
      "contact_frac": 0.32
    },
    {
      "gx": 40,
      "gy": 0,
      "cx": 0.046545,
      "cy": -0.047243,
      "rx": 0.0,
      "ry": 0.0,
      "rz": 4.712389,
      "depth_min": 0.001,
      "depth_max": 0.001,
      "contact_frac": 0.202
    },
    {
      "gx": 41,
      "gy": 0,
      "cx": 0.062799,
      "cy": -0.042449,
      "rx": 0.0,
      "ry": 0.0,
      "rz": 4.712389,
      "depth_min": 0.001,
      "depth_max": 0.001,
      "contact_frac": 0.448
    },
    {
      "gx": 42,
      "gy": 0,
      "cx": 0.066234,
      "cy": -0.048359,
      "rx": 0.0,
      "ry": 0.0,
      "rz": 4.712389,
      "depth_min": 0.001,
      "depth_max": 0.001,
      "contact_frac": 0.139
    },
    {
      "gx": 43,
      "gy": 0,
      "cx": 0.070358,
      "cy": -0.042409,
      "rx": 0.0,
      "ry": 0.0,
      "rz": 4.712389,
      "depth_min": 0.001,
      "depth_max": 0.001,
      "contact_frac": 0.224
    },
    {
      "gx": 44,
      "gy": 0,
      "cx": 0.070614,
      "cy": -0.043256,
      "rx": 0.0,
      "ry": 0.0,
      "rz": 4.712389,
      "depth_min": 0.001,
      "depth_max": 0.001,
      "contact_frac": 0.193
    },
    {
      "gx": 45,
      "gy": 0,
      "cx": 0.050311,
      "cy": -0.041816,
      "rx": 0.0,
      "ry": 0.0,
      "rz": 4.712389,
      "depth_min": 0.001,
      "depth_max": 0.001,
      "contact_frac": 0.496
    },
    {
      "gx": 46,
      "gy": 0,
      "cx": 0.049997,
      "cy": -0.037728,
      "rx": 0.0,
      "ry": 0.0,
      "rz": 4.712389,
      "depth_min": 0.001,
      "depth_max": 0.001,
      "contact_frac": 0.339
    },
    {
      "gx": 47,
      "gy": 0,
      "cx": 0.038832,
      "cy": -0.042058,
      "rx": 0.0,
      "ry": 0.0,
      "rz": 4.712389,
      "depth_min": 0.001,
      "depth_max": 0.001,
      "contact_frac": 0.488
    },
    {
      "gx": 48,
      "gy": 0,
      "cx": 0.0224,
      "cy": -0.03491,
      "rx": 0.0,
      "ry": 0.0,
      "rz": 4.712389,
      "depth_min": 0.001,
      "depth_max": 0.001,
      "contact_frac": 0.206
    },
    {
      "gx": 49,
      "gy": 0,
      "cx": 0.050787,
      "cy": -0.035589,
      "rx": 0.0,
      "ry": 0.0,
      "rz": 4.712389,
      "depth_min": 0.001,
      "depth_max": 0.001,
      "contact_frac": 0.239
    },
    {
      "gx": 50,
      "gy": 0,
      "cx": 0.020226,
      "cy": -0.035276,
      "rx": 0.0,
      "ry": 0.0,
      "rz": 4.712389,
      "depth_min": 0.001,
      "depth_max": 0.001,
      "contact_frac": 0.211
    },
    {
      "gx": 51,
      "gy": 0,
      "cx": 0.033862,
      "cy": -0.048638,
      "rx": 0.0,
      "ry": 0.0,
      "rz": 4.712389,
      "depth_min": 0.001,
      "depth_max": 0.001,
      "contact_frac": 0.147
    },
    {
      "gx": 52,
      "gy": 0,
      "cx": 0.036728,
      "cy": -0.033557,
      "rx": 0.0,
      "ry": 0.0,
      "rz": 4.712389,
      "depth_min": 0.001,
      "depth_max": 0.001,
      "contact_frac": 0.151
    },
    {
      "gx": 53,
      "gy": 0,
      "cx": 0.071451,
      "cy": -0.039797,
      "rx": 0.0,
      "ry": 0.0,
      "rz": 4.712389,
      "depth_min": 0.001,
      "depth_max": 0.001,
      "contact_frac": 0.197
    },
    {
      "gx": 54,
      "gy": 0,
      "cx": 0.012141,
      "cy": -0.04544,
      "rx": 0.0,
      "ry": 0.0,
      "rz": 4.712389,
      "depth_min": 0.001,
      "depth_max": 0.001,
      "contact_frac": 0.172
    },
    {
      "gx": 55,
      "gy": 0,
      "cx": 0.032565,
      "cy": -0.034436,
      "rx": 0.0,
      "ry": 0.0,
      "rz": 4.712389,
      "depth_min": 0.001,
      "depth_max": 0.001,
      "contact_frac": 0.202
    },
    {
      "gx": 56,
      "gy": 0,
      "cx": 0.011502,
      "cy": -0.036917,
      "rx": 0.0,
      "ry": 0.0,
      "rz": 4.712389,
      "depth_min": 0.001,
      "depth_max": 0.001,
      "contact_frac": 0.149
    },
    {
      "gx": 57,
      "gy": 0,
      "cx": 0.011088,
      "cy": -0.039691,
      "rx": 0.0,
      "ry": 0.0,
      "rz": 4.712389,
      "depth_min": 0.001,
      "depth_max": 0.001,
      "contact_frac": 0.204
    },
    {
      "gx": 58,
      "gy": 0,
      "cx": 0.044141,
      "cy": -0.037526,
      "rx": 0.0,
      "ry": 0.0,
      "rz": 4.712389,
      "depth_min": 0.001,
      "depth_max": 0.001,
      "contact_frac": 0.331
    },
    {
      "gx": 59,
      "gy": 0,
      "cx": 0.054418,
      "cy": -0.047425,
      "rx": 0.0,
      "ry": 0.0,
      "rz": 4.712389,
      "depth_min": 0.001,
      "depth_max": 0.001,
      "contact_frac": 0.194
    },
    {
      "gx": 60,
      "gy": 0,
      "cx": 0.011682,
      "cy": -0.046579,
      "rx": 0.0,
      "ry": 0.0,
      "rz": 4.712389,
      "depth_min": 0.001,
      "depth_max": 0.001,
      "contact_frac": 0.135
    },
    {
      "gx": 61,
      "gy": 0,
      "cx": 0.064317,
      "cy": -0.03329,
      "rx": 0.0,
      "ry": 0.0,
      "rz": 4.712389,
      "depth_min": 0.001,
      "depth_max": 0.001,
      "contact_frac": 0.136
    },
    {
      "gx": 62,
      "gy": 0,
      "cx": 0.063472,
      "cy": -0.033839,
      "rx": 0.0,
      "ry": 0.0,
      "rz": 4.712389,
      "depth_min": 0.001,
      "depth_max": 0.001,
      "contact_frac": 0.159
    },
    {
      "gx": 63,
      "gy": 0,
      "cx": 0.033301,
      "cy": -0.040901,
      "rx": 0.0,
      "ry": 0.0,
      "rz": 4.712389,
      "depth_min": 0.001,
      "depth_max": 0.001,
      "contact_frac": 0.528
    },
    {
      "gx": 64,
      "gy": 0,
      "cx": 0.053433,
      "cy": -0.035874,
      "rx": 0.0,
      "ry": 0.0,
      "rz": 4.712389,
      "depth_min": 0.001,
      "depth_max": 0.001,
      "contact_frac": 0.24
    },
    {
      "gx": 65,
      "gy": 0,
      "cx": 0.050033,
      "cy": -0.050208,
      "rx": 0.0,
      "ry": 0.0,
      "rz": 4.712389,
      "depth_min": 0.001,
      "depth_max": 0.001,
      "contact_frac": 0.074
    },
    {
      "gx": 66,
      "gy": 0,
      "cx": 0.011058,
      "cy": -0.038986,
      "rx": 0.0,
      "ry": 0.0,
      "rz": 4.712389,
      "depth_min": 0.001,
      "depth_max": 0.001,
      "contact_frac": 0.188
    },
    {
      "gx": 67,
      "gy": 0,
      "cx": 0.023973,
      "cy": -0.050244,
      "rx": 0.0,
      "ry": 0.0,
      "rz": 4.712389,
      "depth_min": 0.001,
      "depth_max": 0.001,
      "contact_frac": 0.076
    },
    {
      "gx": 68,
      "gy": 0,
      "cx": 0.040439,
      "cy": -0.039569,
      "rx": 0.0,
      "ry": 0.0,
      "rz": 4.712389,
      "depth_min": 0.001,
      "depth_max": 0.001,
      "contact_frac": 0.446
    },
    {
      "gx": 69,
      "gy": 0,
      "cx": 0.052775,
      "cy": -0.046133,
      "rx": 0.0,
      "ry": 0.0,
      "rz": 4.712389,
      "depth_min": 0.001,
      "depth_max": 0.001,
      "contact_frac": 0.241
    },
    {
      "gx": 70,
      "gy": 0,
      "cx": 0.0146,
      "cy": -0.036041,
      "rx": 0.0,
      "ry": 0.0,
      "rz": 4.712389,
      "depth_min": 0.001,
      "depth_max": 0.001,
      "contact_frac": 0.185
    },
    {
      "gx": 71,
      "gy": 0,
      "cx": 0.022724,
      "cy": -0.046171,
      "rx": 0.0,
      "ry": 0.0,
      "rz": 4.712389,
      "depth_min": 0.001,
      "depth_max": 0.001,
      "contact_frac": 0.231
    },
    {
      "gx": 72,
      "gy": 0,
      "cx": 0.038428,
      "cy": -0.034169,
      "rx": 0.0,
      "ry": 0.0,
      "rz": 4.712389,
      "depth_min": 0.001,
      "depth_max": 0.001,
      "contact_frac": 0.169
    },
    {
      "gx": 73,
      "gy": 0,
      "cx": 0.059376,
      "cy": -0.035352,
      "rx": 0.0,
      "ry": 0.0,
      "rz": 4.712389,
      "depth_min": 0.001,
      "depth_max": 0.001,
      "contact_frac": 0.21
    },
    {
      "gx": 74,
      "gy": 0,
      "cx": 0.044836,
      "cy": -0.032316,
      "rx": 0.0,
      "ry": 0.0,
      "rz": 4.712389,
      "depth_min": 0.001,
      "depth_max": 0.001,
      "contact_frac": 0.103
    },
    {
      "gx": 75,
      "gy": 0,
      "cx": 0.028821,
      "cy": -0.035806,
      "rx": 0.0,
      "ry": 0.0,
      "rz": 4.712389,
      "depth_min": 0.001,
      "depth_max": 0.001,
      "contact_frac": 0.256
    },
    {
      "gx": 76,
      "gy": 0,
      "cx": 0.059146,
      "cy": -0.035489,
      "rx": 0.0,
      "ry": 0.0,
      "rz": 4.712389,
      "depth_min": 0.001,
      "depth_max": 0.001,
      "contact_frac": 0.213
    },
    {
      "gx": 77,
      "gy": 0,
      "cx": 0.018107,
      "cy": -0.042806,
      "rx": 0.0,
      "ry": 0.0,
      "rz": 4.712389,
      "depth_min": 0.001,
      "depth_max": 0.001,
      "contact_frac": 0.428
    },
    {
      "gx": 78,
      "gy": 0,
      "cx": 0.015712,
      "cy": -0.043786,
      "rx": 0.0,
      "ry": 0.0,
      "rz": 4.712389,
      "depth_min": 0.001,
      "depth_max": 0.001,
      "contact_frac": 0.294
    },
    {
      "gx": 79,
      "gy": 0,
      "cx": 0.044897,
      "cy": -0.042649,
      "rx": 0.0,
      "ry": 0.0,
      "rz": 4.712389,
      "depth_min": 0.001,
      "depth_max": 0.001,
      "contact_frac": 0.453
    },
    {
      "gx": 80,
      "gy": 0,
      "cx": 0.013178,
      "cy": -0.048132,
      "rx": 0.0,
      "ry": 0.0,
      "rz": 4.712389,
      "depth_min": 0.001,
      "depth_max": 0.001,
      "contact_frac": 0.12
    },
    {
      "gx": 81,
      "gy": 0,
      "cx": 0.067822,
      "cy": -0.041608,
      "rx": 0.0,
      "ry": 0.0,
      "rz": 4.712389,
      "depth_min": 0.001,
      "depth_max": 0.001,
      "contact_frac": 0.343
    },
    {
      "gx": 82,
      "gy": 0,
      "cx": 0.010336,
      "cy": -0.03821,
      "rx": 0.0,
      "ry": 0.0,
      "rz": 4.712389,
      "depth_min": 0.001,
      "depth_max": 0.001,
      "contact_frac": 0.15
    },
    {
      "gx": 83,
      "gy": 0,
      "cx": 0.050065,
      "cy": -0.048184,
      "rx": 0.0,
      "ry": 0.0,
      "rz": 4.712389,
      "depth_min": 0.001,
      "depth_max": 0.001,
      "contact_frac": 0.156
    },
    {
      "gx": 84,
      "gy": 0,
      "cx": 0.06354,
      "cy": -0.038003,
      "rx": 0.0,
      "ry": 0.0,
      "rz": 4.712389,
      "depth_min": 0.001,
      "depth_max": 0.001,
      "contact_frac": 0.354
    },
    {
      "gx": 85,
      "gy": 0,
      "cx": 0.010726,
      "cy": -0.045838,
      "rx": 0.0,
      "ry": 0.0,
      "rz": 4.712389,
      "depth_min": 0.001,
      "depth_max": 0.001,
      "contact_frac": 0.129
    },
    {
      "gx": 86,
      "gy": 0,
      "cx": 0.033106,
      "cy": -0.047765,
      "rx": 0.0,
      "ry": 0.0,
      "rz": 4.712389,
      "depth_min": 0.001,
      "depth_max": 0.001,
      "contact_frac": 0.183
    },
    {
      "gx": 87,
      "gy": 0,
      "cx": 0.035879,
      "cy": -0.045737,
      "rx": 0.0,
      "ry": 0.0,
      "rz": 4.712389,
      "depth_min": 0.001,
      "depth_max": 0.001,
      "contact_frac": 0.266
    },
    {
      "gx": 88,
      "gy": 0,
      "cx": 0.046548,
      "cy": -0.036635,
      "rx": 0.0,
      "ry": 0.0,
      "rz": 4.712389,
      "depth_min": 0.001,
      "depth_max": 0.001,
      "contact_frac": 0.279
    },
    {
      "gx": 89,
      "gy": 0,
      "cx": 0.07193,
      "cy": -0.036874,
      "rx": 0.0,
      "ry": 0.0,
      "rz": 4.712389,
      "depth_min": 0.001,
      "depth_max": 0.001,
      "contact_frac": 0.131
    },
    {
      "gx": 90,
      "gy": 0,
      "cx": 0.033457,
      "cy": -0.043774,
      "rx": 0.0,
      "ry": 0.0,
      "rz": 4.712389,
      "depth_min": 0.001,
      "depth_max": 0.001,
      "contact_frac": 0.382
    },
    {
      "gx": 91,
      "gy": 0,
      "cx": 0.024469,
      "cy": -0.036263,
      "rx": 0.0,
      "ry": 0.0,
      "rz": 4.712389,
      "depth_min": 0.001,
      "depth_max": 0.001,
      "contact_frac": 0.256
    },
    {
      "gx": 92,
      "gy": 0,
      "cx": 0.037343,
      "cy": -0.041515,
      "rx": 0.0,
      "ry": 0.0,
      "rz": 4.712389,
      "depth_min": 0.001,
      "depth_max": 0.001,
      "contact_frac": 0.529
    },
    {
      "gx": 93,
      "gy": 0,
      "cx": 0.065127,
      "cy": -0.035674,
      "rx": 0.0,
      "ry": 0.0,
      "rz": 4.712389,
      "depth_min": 0.001,
      "depth_max": 0.001,
      "contact_frac": 0.23
    },
    {
      "gx": 94,
      "gy": 0,
      "cx": 0.029076,
      "cy": -0.042654,
      "rx": 0.0,
      "ry": 0.0,
      "rz": 4.712389,
      "depth_min": 0.001,
      "depth_max": 0.001,
      "contact_frac": 0.448
    },
    {
      "gx": 95,
      "gy": 0,
      "cx": 0.031989,
      "cy": -0.037662,
      "rx": 0.0,
      "ry": 0.0,
      "rz": 4.712389,
      "depth_min": 0.001,
      "depth_max": 0.001,
      "contact_frac": 0.351
    },
    {
      "gx": 96,
      "gy": 0,
      "cx": 0.028234,
      "cy": -0.038278,
      "rx": 0.0,
      "ry": 0.0,
      "rz": 4.712389,
      "depth_min": 0.001,
      "depth_max": 0.001,
      "contact_frac": 0.385
    },
    {
      "gx": 97,
      "gy": 0,
      "cx": 0.02785,
      "cy": -0.037913,
      "rx": 0.0,
      "ry": 0.0,
      "rz": 4.712389,
      "depth_min": 0.001,
      "depth_max": 0.001,
      "contact_frac": 0.362
    },
    {
      "gx": 98,
      "gy": 0,
      "cx": 0.016779,
      "cy": -0.033874,
      "rx": 0.0,
      "ry": 0.0,
      "rz": 4.712389,
      "depth_min": 0.001,
      "depth_max": 0.001,
      "contact_frac": 0.162
    },
    {
      "gx": 99,
      "gy": 0,
      "cx": 0.05369,
      "cy": -0.047283,
      "rx": 0.0,
      "ry": 0.0,
      "rz": 4.712389,
      "depth_min": 0.001,
      "depth_max": 0.001,
      "contact_frac": 0.199
    },
    {
      "gx": 100,
      "gy": 0,
      "cx": 0.07023,
      "cy": -0.047339,
      "rx": 0.0,
      "ry": 0.0,
      "rz": 4.712389,
      "depth_min": 0.001,
      "depth_max": 0.001,
      "contact_frac": 0.11
    },
    {
      "gx": 101,
      "gy": 0,
      "cx": 0.02957,
      "cy": -0.045181,
      "rx": 0.0,
      "ry": 0.0,
      "rz": 4.712389,
      "depth_min": 0.001,
      "depth_max": 0.001,
      "contact_frac": 0.299
    },
    {
      "gx": 102,
      "gy": 0,
      "cx": 0.061036,
      "cy": -0.048306,
      "rx": 0.0,
      "ry": 0.0,
      "rz": 4.712389,
      "depth_min": 0.001,
      "depth_max": 0.001,
      "contact_frac": 0.158
    },
    {
      "gx": 103,
      "gy": 0,
      "cx": 0.058312,
      "cy": -0.040925,
      "rx": 0.0,
      "ry": 0.0,
      "rz": 4.712389,
      "depth_min": 0.001,
      "depth_max": 0.001,
      "contact_frac": 0.481
    },
    {
      "gx": 104,
      "gy": 0,
      "cx": 0.010965,
      "cy": -0.034283,
      "rx": 0.0,
      "ry": 0.0,
      "rz": 4.712389,
      "depth_min": 0.001,
      "depth_max": 0.001,
      "contact_frac": 0.092
    },
    {
      "gx": 105,
      "gy": 0,
      "cx": 0.011249,
      "cy": -0.041173,
      "rx": 0.0,
      "ry": 0.0,
      "rz": 4.712389,
      "depth_min": 0.001,
      "depth_max": 0.001,
      "contact_frac": 0.226
    },
    {
      "gx": 106,
      "gy": 0,
      "cx": 0.040022,
      "cy": -0.048655,
      "rx": 0.0,
      "ry": 0.0,
      "rz": 4.712389,
      "depth_min": 0.001,
      "depth_max": 0.001,
      "contact_frac": 0.145
    },
    {
      "gx": 107,
      "gy": 0,
      "cx": 0.042702,
      "cy": -0.031879,
      "rx": 0.0,
      "ry": 0.0,
      "rz": 4.712389,
      "depth_min": 0.001,
      "depth_max": 0.001,
      "contact_frac": 0.083
    },
    {
      "gx": 108,
      "gy": 0,
      "cx": 0.018966,
      "cy": -0.04786,
      "rx": 0.0,
      "ry": 0.0,
      "rz": 4.712389,
      "depth_min": 0.001,
      "depth_max": 0.001,
      "contact_frac": 0.168
    },
    {
      "gx": 109,
      "gy": 0,
      "cx": 0.031167,
      "cy": -0.035215,
      "rx": 0.0,
      "ry": 0.0,
      "rz": 4.712389,
      "depth_min": 0.001,
      "depth_max": 0.001,
      "contact_frac": 0.232
    },
    {
      "gx": 110,
      "gy": 0,
      "cx": 0.013351,
      "cy": -0.047912,
      "rx": 0.0,
      "ry": 0.0,
      "rz": 4.712389,
      "depth_min": 0.001,
      "depth_max": 0.001,
      "contact_frac": 0.127
    },
    {
      "gx": 111,
      "gy": 0,
      "cx": 0.064849,
      "cy": -0.043003,
      "rx": 0.0,
      "ry": 0.0,
      "rz": 4.712389,
      "depth_min": 0.001,
      "depth_max": 0.001,
      "contact_frac": 0.423
    },
    {
      "gx": 112,
      "gy": 0,
      "cx": 0.010432,
      "cy": -0.034026,
      "rx": 0.0,
      "ry": 0.0,
      "rz": 4.712389,
      "depth_min": 0.001,
      "depth_max": 0.001,
      "contact_frac": 0.078
    },
    {
      "gx": 113,
      "gy": 0,
      "cx": 0.019079,
      "cy": -0.032431,
      "rx": 0.0,
      "ry": 0.0,
      "rz": 4.712389,
      "depth_min": 0.001,
      "depth_max": 0.001,
      "contact_frac": 0.1
    },
    {
      "gx": 114,
      "gy": 0,
      "cx": 0.011533,
      "cy": -0.038291,
      "rx": 0.0,
      "ry": 0.0,
      "rz": 4.712389,
      "depth_min": 0.001,
      "depth_max": 0.001,
      "contact_frac": 0.182
    },
    {
      "gx": 115,
      "gy": 0,
      "cx": 0.01934,
      "cy": -0.041403,
      "rx": 0.0,
      "ry": 0.0,
      "rz": 4.712389,
      "depth_min": 0.001,
      "depth_max": 0.001,
      "contact_frac": 0.496
    },
    {
      "gx": 116,
      "gy": 0,
      "cx": 0.070623,
      "cy": -0.04326,
      "rx": 0.0,
      "ry": 0.0,
      "rz": 4.712389,
      "depth_min": 0.001,
      "depth_max": 0.001,
      "contact_frac": 0.193
    },
    {
      "gx": 117,
      "gy": 0,
      "cx": 0.068873,
      "cy": -0.033209,
      "rx": 0.0,
      "ry": 0.0,
      "rz": 4.712389,
      "depth_min": 0.001,
      "depth_max": 0.001,
      "contact_frac": 0.105
    },
    {
      "gx": 118,
      "gy": 0,
      "cx": 0.020152,
      "cy": -0.034435,
      "rx": 0.0,
      "ry": 0.0,
      "rz": 4.712389,
      "depth_min": 0.001,
      "depth_max": 0.001,
      "contact_frac": 0.182
    },
    {
      "gx": 119,
      "gy": 0,
      "cx": 0.053334,
      "cy": -0.041425,
      "rx": 0.0,
      "ry": 0.0,
      "rz": 4.712389,
      "depth_min": 0.001,
      "depth_max": 0.001,
      "contact_frac": 0.51
    },
    {
      "gx": 120,
      "gy": 0,
      "cx": 0.043888,
      "cy": -0.039818,
      "rx": 0.0,
      "ry": 0.0,
      "rz": 4.712389,
      "depth_min": 0.001,
      "depth_max": 0.001,
      "contact_frac": 0.466
    },
    {
      "gx": 121,
      "gy": 0,
      "cx": 0.033665,
      "cy": -0.047819,
      "rx": 0.0,
      "ry": 0.0,
      "rz": 4.712389,
      "depth_min": 0.001,
      "depth_max": 0.001,
      "contact_frac": 0.181
    },
    {
      "gx": 122,
      "gy": 0,
      "cx": 0.031445,
      "cy": -0.045707,
      "rx": 0.0,
      "ry": 0.0,
      "rz": 4.712389,
      "depth_min": 0.001,
      "depth_max": 0.001,
      "contact_frac": 0.273
    },
    {
      "gx": 123,
      "gy": 0,
      "cx": 0.061043,
      "cy": -0.035642,
      "rx": 0.0,
      "ry": 0.0,
      "rz": 4.712389,
      "depth_min": 0.001,
      "depth_max": 0.001,
      "contact_frac": 0.219
    },
    {
      "gx": 124,
      "gy": 0,
      "cx": 0.030701,
      "cy": -0.047968,
      "rx": 0.0,
      "ry": 0.0,
      "rz": 4.712389,
      "depth_min": 0.001,
      "depth_max": 0.001,
      "contact_frac": 0.172
    },
    {
      "gx": 125,
      "gy": 0,
      "cx": 0.070431,
      "cy": -0.043094,
      "rx": 0.0,
      "ry": 0.0,
      "rz": 4.712389,
      "depth_min": 0.001,
      "depth_max": 0.001,
      "contact_frac": 0.202
    },
    {
      "gx": 126,
      "gy": 0,
      "cx": 0.043299,
      "cy": -0.042535,
      "rx": 0.0,
      "ry": 0.0,
      "rz": 4.712389,
      "depth_min": 0.001,
      "depth_max": 0.001,
      "contact_frac": 0.455
    },
    {
      "gx": 127,
      "gy": 0,
      "cx": 0.065856,
      "cy": -0.032405,
      "rx": 0.0,
      "ry": 0.0,
      "rz": 4.712389,
      "depth_min": 0.001,
      "depth_max": 0.001,
      "contact_frac": 0.107
    },
    {
      "gx": 128,
      "gy": 0,
      "cx": 0.069736,
      "cy": -0.04578,
      "rx": 0.0,
      "ry": 0.0,
      "rz": 4.712389,
      "depth_min": 0.001,
      "depth_max": 0.001,
      "contact_frac": 0.163
    },
    {
      "gx": 129,
      "gy": 0,
      "cx": 0.045248,
      "cy": -0.036718,
      "rx": 0.0,
      "ry": 0.0,
      "rz": 4.712389,
      "depth_min": 0.001,
      "depth_max": 0.001,
      "contact_frac": 0.283
    },
    {
      "gx": 130,
      "gy": 0,
      "cx": 0.054307,
      "cy": -0.049739,
      "rx": 0.0,
      "ry": 0.0,
      "rz": 4.712389,
      "depth_min": 0.001,
      "depth_max": 0.001,
      "contact_frac": 0.095
    },
    {
      "gx": 131,
      "gy": 0,
      "cx": 0.033728,
      "cy": -0.040491,
      "rx": 0.0,
      "ry": 0.0,
      "rz": 4.712389,
      "depth_min": 0.001,
      "depth_max": 0.001,
      "contact_frac": 0.535
    },
    {
      "gx": 132,
      "gy": 0,
      "cx": 0.053783,
      "cy": -0.037316,
      "rx": 0.0,
      "ry": 0.0,
      "rz": 4.712389,
      "depth_min": 0.001,
      "depth_max": 0.001,
      "contact_frac": 0.305
    },
    {
      "gx": 133,
      "gy": 0,
      "cx": 0.051459,
      "cy": -0.035503,
      "rx": 0.0,
      "ry": 0.0,
      "rz": 4.712389,
      "depth_min": 0.001,
      "depth_max": 0.001,
      "contact_frac": 0.236
    },
    {
      "gx": 134,
      "gy": 0,
      "cx": 0.063292,
      "cy": -0.045093,
      "rx": 0.0,
      "ry": 0.0,
      "rz": 4.712389,
      "depth_min": 0.001,
      "depth_max": 0.001,
      "contact_frac": 0.306
    },
    {
      "gx": 135,
      "gy": 0,
      "cx": 0.019957,
      "cy": -0.046153,
      "rx": 0.0,
      "ry": 0.0,
      "rz": 4.712389,
      "depth_min": 0.001,
      "depth_max": 0.001,
      "contact_frac": 0.238
    },
    {
      "gx": 136,
      "gy": 0,
      "cx": 0.071336,
      "cy": -0.041959,
      "rx": 0.0,
      "ry": 0.0,
      "rz": 4.712389,
      "depth_min": 0.001,
      "depth_max": 0.001,
      "contact_frac": 0.202
    },
    {
      "gx": 137,
      "gy": 0,
      "cx": 0.057662,
      "cy": -0.033823,
      "rx": 0.0,
      "ry": 0.0,
      "rz": 4.712389,
      "depth_min": 0.001,
      "depth_max": 0.001,
      "contact_frac": 0.151
    },
    {
      "gx": 138,
      "gy": 0,
      "cx": 0.035426,
      "cy": -0.045098,
      "rx": 0.0,
      "ry": 0.0,
      "rz": 4.712389,
      "depth_min": 0.001,
      "depth_max": 0.001,
      "contact_frac": 0.302
    },
    {
      "gx": 139,
      "gy": 0,
      "cx": 0.037581,
      "cy": -0.03238,
      "rx": 0.0,
      "ry": 0.0,
      "rz": 4.712389,
      "depth_min": 0.001,
      "depth_max": 0.001,
      "contact_frac": 0.104
    },
    {
      "gx": 140,
      "gy": 0,
      "cx": 0.065664,
      "cy": -0.045265,
      "rx": 0.0,
      "ry": 0.0,
      "rz": 4.712389,
      "depth_min": 0.001,
      "depth_max": 0.001,
      "contact_frac": 0.3
    },
    {
      "gx": 141,
      "gy": 0,
      "cx": 0.043065,
      "cy": -0.041984,
      "rx": 0.0,
      "ry": 0.0,
      "rz": 4.712389,
      "depth_min": 0.001,
      "depth_max": 0.001,
      "contact_frac": 0.488
    },
    {
      "gx": 142,
      "gy": 0,
      "cx": 0.031559,
      "cy": -0.046779,
      "rx": 0.0,
      "ry": 0.0,
      "rz": 4.712389,
      "depth_min": 0.001,
      "depth_max": 0.001,
      "contact_frac": 0.225
    },
    {
      "gx": 143,
      "gy": 0,
      "cx": 0.011297,
      "cy": -0.034959,
      "rx": 0.0,
      "ry": 0.0,
      "rz": 4.712389,
      "depth_min": 0.001,
      "depth_max": 0.001,
      "contact_frac": 0.108
    },
    {
      "gx": 144,
      "gy": 0,
      "cx": 0.064686,
      "cy": -0.047208,
      "rx": 0.0,
      "ry": 0.0,
      "rz": 4.712389,
      "depth_min": 0.001,
      "depth_max": 0.001,
      "contact_frac": 0.209
    },
    {
      "gx": 145,
      "gy": 0,
      "cx": 0.070463,
      "cy": -0.041309,
      "rx": 0.0,
      "ry": 0.0,
      "rz": 4.712389,
      "depth_min": 0.001,
      "depth_max": 0.001,
      "contact_frac": 0.236
    },
    {
      "gx": 146,
      "gy": 0,
      "cx": 0.033226,
      "cy": -0.04811,
      "rx": 0.0,
      "ry": 0.0,
      "rz": 4.712389,
      "depth_min": 0.001,
      "depth_max": 0.001,
      "contact_frac": 0.167
    },
    {
      "gx": 147,
      "gy": 0,
      "cx": 0.064149,
      "cy": -0.03272,
      "rx": 0.0,
      "ry": 0.0,
      "rz": 4.712389,
      "depth_min": 0.001,
      "depth_max": 0.001,
      "contact_frac": 0.112
    },
    {
      "gx": 148,
      "gy": 0,
      "cx": 0.01029,
      "cy": -0.037673,
      "rx": 0.0,
      "ry": 0.0,
      "rz": 4.712389,
      "depth_min": 0.001,
      "depth_max": 0.001,
      "contact_frac": 0.138
    },
    {
      "gx": 149,
      "gy": 0,
      "cx": 0.011849,
      "cy": -0.034914,
      "rx": 0.0,
      "ry": 0.0,
      "rz": 4.712389,
      "depth_min": 0.001,
      "depth_max": 0.001,
      "contact_frac": 0.113
    },
    {
      "gx": 150,
      "gy": 0,
      "cx": 0.042487,
      "cy": -0.035345,
      "rx": 0.0,
      "ry": 0.0,
      "rz": 4.712389,
      "depth_min": 0.001,
      "depth_max": 0.001,
      "contact_frac": 0.219
    },
    {
      "gx": 151,
      "gy": 0,
      "cx": 0.031984,
      "cy": -0.034833,
      "rx": 0.0,
      "ry": 0.0,
      "rz": 4.712389,
      "depth_min": 0.001,
      "depth_max": 0.001,
      "contact_frac": 0.216
    },
    {
      "gx": 152,
      "gy": 0,
      "cx": 0.011709,
      "cy": -0.046958,
      "rx": 0.0,
      "ry": 0.0,
      "rz": 4.712389,
      "depth_min": 0.001,
      "depth_max": 0.001,
      "contact_frac": 0.128
    },
    {
      "gx": 153,
      "gy": 0,
      "cx": 0.021415,
      "cy": -0.048091,
      "rx": 0.0,
      "ry": 0.0,
      "rz": 4.712389,
      "depth_min": 0.001,
      "depth_max": 0.001,
      "contact_frac": 0.157
    },
    {
      "gx": 154,
      "gy": 0,
      "cx": 0.04695,
      "cy": -0.035438,
      "rx": 0.0,
      "ry": 0.0,
      "rz": 4.712389,
      "depth_min": 0.001,
      "depth_max": 0.001,
      "contact_frac": 0.231
    },
    {
      "gx": 155,
      "gy": 0,
      "cx": 0.033629,
      "cy": -0.041747,
      "rx": 0.0,
      "ry": 0.0,
      "rz": 4.712389,
      "depth_min": 0.001,
      "depth_max": 0.001,
      "contact_frac": 0.527
    },
    {
      "gx": 156,
      "gy": 0,
      "cx": 0.058414,
      "cy": -0.047455,
      "rx": 0.0,
      "ry": 0.0,
      "rz": 4.712389,
      "depth_min": 0.001,
      "depth_max": 0.001,
      "contact_frac": 0.195
    },
    {
      "gx": 157,
      "gy": 0,
      "cx": 0.012551,
      "cy": -0.040243,
      "rx": 0.0,
      "ry": 0.0,
      "rz": 4.712389,
      "depth_min": 0.001,
      "depth_max": 0.001,
      "contact_frac": 0.27
    },
    {
      "gx": 158,
      "gy": 0,
      "cx": 0.02919,
      "cy": -0.03472,
      "rx": 0.0,
      "ry": 0.0,
      "rz": 4.712389,
      "depth_min": 0.001,
      "depth_max": 0.001,
      "contact_frac": 0.213
    },
    {
      "gx": 159,
      "gy": 0,
      "cx": 0.011073,
      "cy": -0.041561,
      "rx": 0.0,
      "ry": 0.0,
      "rz": 4.712389,
      "depth_min": 0.001,
      "depth_max": 0.001,
      "contact_frac": 0.228
    },
    {
      "gx": 160,
      "gy": 0,
      "cx": 0.030006,
      "cy": -0.039308,
      "rx": 0.0,
      "ry": 0.0,
      "rz": 4.712389,
      "depth_min": 0.001,
      "depth_max": 0.001,
      "contact_frac": 0.455
    },
    {
      "gx": 161,
      "gy": 0,
      "cx": 0.010626,
      "cy": -0.046034,
      "rx": 0.0,
      "ry": 0.0,
      "rz": 4.712389,
      "depth_min": 0.001,
      "depth_max": 0.001,
      "contact_frac": 0.126
    },
    {
      "gx": 162,
      "gy": 0,
      "cx": 0.014852,
      "cy": -0.036071,
      "rx": 0.0,
      "ry": 0.0,
      "rz": 4.712389,
      "depth_min": 0.001,
      "depth_max": 0.001,
      "contact_frac": 0.19
    },
    {
      "gx": 163,
      "gy": 0,
      "cx": 0.067459,
      "cy": -0.037202,
      "rx": 0.0,
      "ry": 0.0,
      "rz": 4.712389,
      "depth_min": 0.001,
      "depth_max": 0.001,
      "contact_frac": 0.239
    },
    {
      "gx": 164,
      "gy": 0,
      "cx": 0.062808,
      "cy": -0.04984,
      "rx": 0.0,
      "ry": 0.0,
      "rz": 4.712389,
      "depth_min": 0.001,
      "depth_max": 0.001,
      "contact_frac": 0.097
    },
    {
      "gx": 165,
      "gy": 0,
      "cx": 0.012907,
      "cy": -0.03208,
      "rx": 0.0,
      "ry": 0.0,
      "rz": 4.712389,
      "depth_min": 0.001,
      "depth_max": 0.001,
      "contact_frac": 0.06
    },
    {
      "gx": 166,
      "gy": 0,
      "cx": 0.011587,
      "cy": -0.044973,
      "rx": 0.0,
      "ry": 0.0,
      "rz": 4.712389,
      "depth_min": 0.001,
      "depth_max": 0.001,
      "contact_frac": 0.167
    },
    {
      "gx": 167,
      "gy": 0,
      "cx": 0.071222,
      "cy": -0.046498,
      "rx": 0.0,
      "ry": 0.0,
      "rz": 4.712389,
      "depth_min": 0.001,
      "depth_max": 0.001,
      "contact_frac": 0.111
    },
    {
      "gx": 168,
      "gy": 0,
      "cx": 0.054825,
      "cy": -0.032558,
      "rx": 0.0,
      "ry": 0.0,
      "rz": 4.712389,
      "depth_min": 0.001,
      "depth_max": 0.001,
      "contact_frac": 0.108
    },
    {
      "gx": 169,
      "gy": 0,
      "cx": 0.033731,
      "cy": -0.041213,
      "rx": 0.0,
      "ry": 0.0,
      "rz": 4.712389,
      "depth_min": 0.001,
      "depth_max": 0.001,
      "contact_frac": 0.528
    },
    {
      "gx": 170,
      "gy": 0,
      "cx": 0.041714,
      "cy": -0.043323,
      "rx": 0.0,
      "ry": 0.0,
      "rz": 4.712389,
      "depth_min": 0.001,
      "depth_max": 0.001,
      "contact_frac": 0.4
    },
    {
      "gx": 171,
      "gy": 0,
      "cx": 0.066349,
      "cy": -0.049623,
      "rx": 0.0,
      "ry": 0.0,
      "rz": 4.712389,
      "depth_min": 0.001,
      "depth_max": 0.001,
      "contact_frac": 0.094
    },
    {
      "gx": 172,
      "gy": 0,
      "cx": 0.020332,
      "cy": -0.047425,
      "rx": 0.0,
      "ry": 0.0,
      "rz": 4.712389,
      "depth_min": 0.001,
      "depth_max": 0.001,
      "contact_frac": 0.179
    },
    {
      "gx": 173,
      "gy": 0,
      "cx": 0.040971,
      "cy": -0.038355,
      "rx": 0.0,
      "ry": 0.0,
      "rz": 4.712389,
      "depth_min": 0.001,
      "depth_max": 0.001,
      "contact_frac": 0.366
    },
    {
      "gx": 174,
      "gy": 0,
      "cx": 0.015752,
      "cy": -0.0487,
      "rx": 0.0,
      "ry": 0.0,
      "rz": 4.712389,
      "depth_min": 0.001,
      "depth_max": 0.001,
      "contact_frac": 0.125
    },
    {
      "gx": 175,
      "gy": 0,
      "cx": 0.01124,
      "cy": -0.036712,
      "rx": 0.0,
      "ry": 0.0,
      "rz": 4.712389,
      "depth_min": 0.001,
      "depth_max": 0.001,
      "contact_frac": 0.141
    },
    {
      "gx": 176,
      "gy": 0,
      "cx": 0.051371,
      "cy": -0.047342,
      "rx": 0.0,
      "ry": 0.0,
      "rz": 4.712389,
      "depth_min": 0.001,
      "depth_max": 0.001,
      "contact_frac": 0.192
    },
    {
      "gx": 177,
      "gy": 0,
      "cx": 0.047952,
      "cy": -0.039374,
      "rx": 0.0,
      "ry": 0.0,
      "rz": 4.712389,
      "depth_min": 0.001,
      "depth_max": 0.001,
      "contact_frac": 0.441
    },
    {
      "gx": 178,
      "gy": 0,
      "cx": 0.064173,
      "cy": -0.040433,
      "rx": 0.0,
      "ry": 0.0,
      "rz": 4.712389,
      "depth_min": 0.001,
      "depth_max": 0.001,
      "contact_frac": 0.508
    },
    {
      "gx": 179,
      "gy": 0,
      "cx": 0.062394,
      "cy": -0.045787,
      "rx": 0.0,
      "ry": 0.0,
      "rz": 4.712389,
      "depth_min": 0.001,
      "depth_max": 0.001,
      "contact_frac": 0.27
    },
    {
      "gx": 180,
      "gy": 0,
      "cx": 0.036221,
      "cy": -0.04694,
      "rx": 0.0,
      "ry": 0.0,
      "rz": 4.712389,
      "depth_min": 0.001,
      "depth_max": 0.001,
      "contact_frac": 0.219
    },
    {
      "gx": 181,
      "gy": 0,
      "cx": 0.071822,
      "cy": -0.046265,
      "rx": 0.0,
      "ry": 0.0,
      "rz": 4.712389,
      "depth_min": 0.001,
      "depth_max": 0.001,
      "contact_frac": 0.103
    },
    {
      "gx": 182,
      "gy": 0,
      "cx": 0.052312,
      "cy": -0.035154,
      "rx": 0.0,
      "ry": 0.0,
      "rz": 4.712389,
      "depth_min": 0.001,
      "depth_max": 0.001,
      "contact_frac": 0.217
    },
    {
      "gx": 183,
      "gy": 0,
      "cx": 0.060806,
      "cy": -0.045872,
      "rx": 0.0,
      "ry": 0.0,
      "rz": 4.712389,
      "depth_min": 0.001,
      "depth_max": 0.001,
      "contact_frac": 0.262
    },
    {
      "gx": 184,
      "gy": 0,
      "cx": 0.014885,
      "cy": -0.042802,
      "rx": 0.0,
      "ry": 0.0,
      "rz": 4.712389,
      "depth_min": 0.001,
      "depth_max": 0.001,
      "contact_frac": 0.315
    },
    {
      "gx": 185,
      "gy": 0,
      "cx": 0.038515,
      "cy": -0.036346,
      "rx": 0.0,
      "ry": 0.0,
      "rz": 4.712389,
      "depth_min": 0.001,
      "depth_max": 0.001,
      "contact_frac": 0.258
    },
    {
      "gx": 186,
      "gy": 0,
      "cx": 0.046545,
      "cy": -0.047115,
      "rx": 0.0,
      "ry": 0.0,
      "rz": 4.712389,
      "depth_min": 0.001,
      "depth_max": 0.001,
      "contact_frac": 0.206
    },
    {
      "gx": 187,
      "gy": 0,
      "cx": 0.04713,
      "cy": -0.050265,
      "rx": 0.0,
      "ry": 0.0,
      "rz": 4.712389,
      "depth_min": 0.001,
      "depth_max": 0.001,
      "contact_frac": 0.075
    },
    {
      "gx": 188,
      "gy": 0,
      "cx": 0.016837,
      "cy": -0.036118,
      "rx": 0.0,
      "ry": 0.0,
      "rz": 4.712389,
      "depth_min": 0.001,
      "depth_max": 0.001,
      "contact_frac": 0.244
    },
    {
      "gx": 189,
      "gy": 0,
      "cx": 0.043474,
      "cy": -0.047265,
      "rx": 0.0,
      "ry": 0.0,
      "rz": 4.712389,
      "depth_min": 0.001,
      "depth_max": 0.001,
      "contact_frac": 0.196
    },
    {
      "gx": 190,
      "gy": 0,
      "cx": 0.023613,
      "cy": -0.048374,
      "rx": 0.0,
      "ry": 0.0,
      "rz": 4.712389,
      "depth_min": 0.001,
      "depth_max": 0.001,
      "contact_frac": 0.149
    },
    {
      "gx": 191,
      "gy": 0,
      "cx": 0.037971,
      "cy": -0.03181,
      "rx": 0.0,
      "ry": 0.0,
      "rz": 4.712389,
      "depth_min": 0.001,
      "depth_max": 0.001,
      "contact_frac": 0.081
    },
    {
      "gx": 192,
      "gy": 0,
      "cx": 0.027072,
      "cy": -0.04733,
      "rx": 0.0,
      "ry": 0.0,
      "rz": 4.712389,
      "depth_min": 0.001,
      "depth_max": 0.001,
      "contact_frac": 0.192
    },
    {
      "gx": 193,
      "gy": 0,
      "cx": 0.070688,
      "cy": -0.049188,
      "rx": 0.0,
      "ry": 0.0,
      "rz": 4.712389,
      "depth_min": 0.001,
      "depth_max": 0.001,
      "contact_frac": 0.069
    },
    {
      "gx": 194,
      "gy": 0,
      "cx": 0.044653,
      "cy": -0.044853,
      "rx": 0.0,
      "ry": 0.0,
      "rz": 4.712389,
      "depth_min": 0.001,
      "depth_max": 0.001,
      "contact_frac": 0.316
    },
    {
      "gx": 195,
      "gy": 0,
      "cx": 0.053423,
      "cy": -0.032691,
      "rx": 0.0,
      "ry": 0.0,
      "rz": 4.712389,
      "depth_min": 0.001,
      "depth_max": 0.001,
      "contact_frac": 0.114
    },
    {
      "gx": 196,
      "gy": 0,
      "cx": 0.058479,
      "cy": -0.033116,
      "rx": 0.0,
      "ry": 0.0,
      "rz": 4.712389,
      "depth_min": 0.001,
      "depth_max": 0.001,
      "contact_frac": 0.126
    },
    {
      "gx": 197,
      "gy": 0,
      "cx": 0.040998,
      "cy": -0.037622,
      "rx": 0.0,
      "ry": 0.0,
      "rz": 4.712389,
      "depth_min": 0.001,
      "depth_max": 0.001,
      "contact_frac": 0.317
    },
    {
      "gx": 198,
      "gy": 0,
      "cx": 0.010708,
      "cy": -0.036539,
      "rx": 0.0,
      "ry": 0.0,
      "rz": 4.712389,
      "depth_min": 0.001,
      "depth_max": 0.001,
      "contact_frac": 0.128
    },
    {
      "gx": 199,
      "gy": 0,
      "cx": 0.026011,
      "cy": -0.036887,
      "rx": 0.0,
      "ry": 0.0,
      "rz": 4.712389,
      "depth_min": 0.001,
      "depth_max": 0.001,
      "contact_frac": 0.293
    }
  ],
  "_rotation_name": "+Z up (original) + Z+270\u00b0",
  "_rotation_degrees": [
    0.0,
    0.0,
    270.0
  ],
  "_sensor_length_mm": 5.0,
  "_sensor_step": 0.006,
  "_target_size_mm": 82.0,
  "_grid": "random-200",
  "_overlap_pct": 40.0,
  "_sampling_method": "random",
  "_use_normal_rotation": false
}