{
  "obj": "pattern_01_2_lines_angle_1_2",
  "base_rotation": [
    0.0,
    0.0,
    1.5707963267948966
  ],
  "rotation_step": 0.0,
  "fixed_scale": 1000.0,
  "X_MIN": -0.06132,
  "X_MAX": -0.02073,
  "Y_MIN": 0.01,
  "Y_MAX": 0.072,
  "NUM_OBJ_SAMPLES": 200,
  "OBJ_DEPTH_MIN": 0.001,
  "OBJ_DEPTH_MAX": 0.001,
  "z_anchor": 0.001717537411721536,
  "valid_cells": [
    {
      "gx": 0,
      "gy": 0,
      "cx": -0.039976,
      "cy": 0.035119,
      "rx": 0.0,
      "ry": 0.0,
      "rz": 1.570796,
      "depth_min": 0.001,
      "depth_max": 0.001,
      "contact_frac": 0.263
    },
    {
      "gx": 1,
      "gy": 0,
      "cx": -0.037018,
      "cy": 0.051942,
      "rx": 0.0,
      "ry": 0.0,
      "rz": 1.570796,
      "depth_min": 0.001,
      "depth_max": 0.001,
      "contact_frac": 0.101
    },
    {
      "gx": 2,
      "gy": 0,
      "cx": -0.031256,
      "cy": 0.031766,
      "rx": 0.0,
      "ry": 0.0,
      "rz": 1.570796,
      "depth_min": 0.001,
      "depth_max": 0.001,
      "contact_frac": 0.072
    },
    {
      "gx": 3,
      "gy": 0,
      "cx": -0.038404,
      "cy": 0.052447,
      "rx": 0.0,
      "ry": 0.0,
      "rz": 1.570796,
      "depth_min": 0.001,
      "depth_max": 0.001,
      "contact_frac": 0.104
    },
    {
      "gx": 4,
      "gy": 0,
      "cx": -0.026421,
      "cy": 0.015959,
      "rx": 0.0,
      "ry": 0.0,
      "rz": 1.570796,
      "depth_min": 0.001,
      "depth_max": 0.001,
      "contact_frac": 0.063
    },
    {
      "gx": 5,
      "gy": 0,
      "cx": -0.036026,
      "cy": 0.032507,
      "rx": 0.0,
      "ry": 0.0,
      "rz": 1.570796,
      "depth_min": 0.001,
      "depth_max": 0.001,
      "contact_frac": 0.204
    },
    {
      "gx": 6,
      "gy": 0,
      "cx": -0.053252,
      "cy": 0.064413,
      "rx": 0.0,
      "ry": 0.0,
      "rz": 1.570796,
      "depth_min": 0.001,
      "depth_max": 0.001,
      "contact_frac": 0.075
    },
    {
      "gx": 7,
      "gy": 0,
      "cx": -0.04197,
      "cy": 0.053741,
      "rx": 0.0,
      "ry": 0.0,
      "rz": 1.570796,
      "depth_min": 0.001,
      "depth_max": 0.001,
      "contact_frac": 0.18
    },
    {
      "gx": 8,
      "gy": 0,
      "cx": -0.029817,
      "cy": 0.03023,
      "rx": 0.0,
      "ry": 0.0,
      "rz": 1.570796,
      "depth_min": 0.001,
      "depth_max": 0.001,
      "contact_frac": 0.054
    },
    {
      "gx": 9,
      "gy": 0,
      "cx": -0.048256,
      "cy": 0.053897,
      "rx": 0.0,
      "ry": 0.0,
      "rz": 1.570796,
      "depth_min": 0.001,
      "depth_max": 0.001,
      "contact_frac": 0.135
    },
    {
      "gx": 10,
      "gy": 0,
      "cx": -0.024914,
      "cy": 0.014262,
      "rx": 0.0,
      "ry": 0.0,
      "rz": 1.570796,
      "depth_min": 0.001,
      "depth_max": 0.001,
      "contact_frac": 0.053
    },
    {
      "gx": 11,
      "gy": 0,
      "cx": -0.046191,
      "cy": 0.059536,
      "rx": 0.0,
      "ry": 0.0,
      "rz": 1.570796,
      "depth_min": 0.001,
      "depth_max": 0.001,
      "contact_frac": 0.086
    },
    {
      "gx": 12,
      "gy": 0,
      "cx": -0.04005,
      "cy": 0.055801,
      "rx": 0.0,
      "ry": 0.0,
      "rz": 1.570796,
      "depth_min": 0.001,
      "depth_max": 0.001,
      "contact_frac": 0.1
    },
    {
      "gx": 13,
      "gy": 0,
      "cx": -0.043047,
      "cy": 0.051391,
      "rx": 0.0,
      "ry": 0.0,
      "rz": 1.570796,
      "depth_min": 0.001,
      "depth_max": 0.001,
      "contact_frac": 0.251
    },
    {
      "gx": 14,
      "gy": 0,
      "cx": -0.039934,
      "cy": 0.06017,
      "rx": 0.0,
      "ry": 0.0,
      "rz": 1.570796,
      "depth_min": 0.001,
      "depth_max": 0.001,
      "contact_frac": 0.093
    },
    {
      "gx": 15,
      "gy": 0,
      "cx": -0.037553,
      "cy": 0.054066,
      "rx": 0.0,
      "ry": 0.0,
      "rz": 1.570796,
      "depth_min": 0.001,
      "depth_max": 0.001,
      "contact_frac": 0.101
    },
    {
      "gx": 16,
      "gy": 0,
      "cx": -0.036481,
      "cy": 0.030028,
      "rx": 0.0,
      "ry": 0.0,
      "rz": 1.570796,
      "depth_min": 0.001,
      "depth_max": 0.001,
      "contact_frac": 0.248
    },
    {
      "gx": 17,
      "gy": 0,
      "cx": -0.05813,
      "cy": 0.062273,
      "rx": 0.0,
      "ry": 0.0,
      "rz": 1.570796,
      "depth_min": 0.001,
      "depth_max": 0.001,
      "contact_frac": 0.052
    },
    {
      "gx": 18,
      "gy": 0,
      "cx": -0.040472,
      "cy": 0.033342,
      "rx": 0.0,
      "ry": 0.0,
      "rz": 1.570796,
      "depth_min": 0.001,
      "depth_max": 0.001,
      "contact_frac": 0.248
    },
    {
      "gx": 19,
      "gy": 0,
      "cx": -0.04005,
      "cy": 0.04071,
      "rx": 0.0,
      "ry": 0.0,
      "rz": 1.570796,
      "depth_min": 0.001,
      "depth_max": 0.001,
      "contact_frac": 0.188
    },
    {
      "gx": 20,
      "gy": 0,
      "cx": -0.036548,
      "cy": 0.050973,
      "rx": 0.0,
      "ry": 0.0,
      "rz": 1.570796,
      "depth_min": 0.001,
      "depth_max": 0.001,
      "contact_frac": 0.074
    },
    {
      "gx": 21,
      "gy": 0,
      "cx": -0.035517,
      "cy": 0.051017,
      "rx": 0.0,
      "ry": 0.0,
      "rz": 1.570796,
      "depth_min": 0.001,
      "depth_max": 0.001,
      "contact_frac": 0.051
    },
    {
      "gx": 22,
      "gy": 0,
      "cx": -0.046024,
      "cy": 0.031783,
      "rx": 0.0,
      "ry": 0.0,
      "rz": 1.570796,
      "depth_min": 0.001,
      "depth_max": 0.001,
      "contact_frac": 0.051
    },
    {
      "gx": 23,
      "gy": 0,
      "cx": -0.037661,
      "cy": 0.02919,
      "rx": 0.0,
      "ry": 0.0,
      "rz": 1.570796,
      "depth_min": 0.001,
      "depth_max": 0.001,
      "contact_frac": 0.267
    },
    {
      "gx": 24,
      "gy": 0,
      "cx": -0.040216,
      "cy": 0.031789,
      "rx": 0.0,
      "ry": 0.0,
      "rz": 1.570796,
      "depth_min": 0.001,
      "depth_max": 0.001,
      "contact_frac": 0.241
    },
    {
      "gx": 25,
      "gy": 0,
      "cx": -0.039173,
      "cy": 0.070513,
      "rx": 0.0,
      "ry": 0.0,
      "rz": 1.570796,
      "depth_min": 0.001,
      "depth_max": 0.001,
      "contact_frac": 0.05
    },
    {
      "gx": 26,
      "gy": 0,
      "cx": -0.037936,
      "cy": 0.055292,
      "rx": 0.0,
      "ry": 0.0,
      "rz": 1.570796,
      "depth_min": 0.001,
      "depth_max": 0.001,
      "contact_frac": 0.101
    },
    {
      "gx": 27,
      "gy": 0,
      "cx": -0.049802,
      "cy": 0.057906,
      "rx": 0.0,
      "ry": 0.0,
      "rz": 1.570796,
      "depth_min": 0.001,
      "depth_max": 0.001,
      "contact_frac": 0.112
    },
    {
      "gx": 28,
      "gy": 0,
      "cx": -0.039614,
      "cy": 0.052584,
      "rx": 0.0,
      "ry": 0.0,
      "rz": 1.570796,
      "depth_min": 0.001,
      "depth_max": 0.001,
      "contact_frac": 0.109
    },
    {
      "gx": 29,
      "gy": 0,
      "cx": -0.046881,
      "cy": 0.058604,
      "rx": 0.0,
      "ry": 0.0,
      "rz": 1.570796,
      "depth_min": 0.001,
      "depth_max": 0.001,
      "contact_frac": 0.089
    },
    {
      "gx": 30,
      "gy": 0,
      "cx": -0.026415,
      "cy": 0.016127,
      "rx": 0.0,
      "ry": 0.0,
      "rz": 1.570796,
      "depth_min": 0.001,
      "depth_max": 0.001,
      "contact_frac": 0.064
    },
    {
      "gx": 31,
      "gy": 0,
      "cx": -0.040089,
      "cy": 0.034259,
      "rx": 0.0,
      "ry": 0.0,
      "rz": 1.570796,
      "depth_min": 0.001,
      "depth_max": 0.001,
      "contact_frac": 0.265
    },
    {
      "gx": 32,
      "gy": 0,
      "cx": -0.040988,
      "cy": 0.032453,
      "rx": 0.0,
      "ry": 0.0,
      "rz": 1.570796,
      "depth_min": 0.001,
      "depth_max": 0.001,
      "contact_frac": 0.207
    },
    {
      "gx": 33,
      "gy": 0,
      "cx": -0.037386,
      "cy": 0.041389,
      "rx": 0.0,
      "ry": 0.0,
      "rz": 1.570796,
      "depth_min": 0.001,
      "depth_max": 0.001,
      "contact_frac": 0.124
    },
    {
      "gx": 34,
      "gy": 0,
      "cx": -0.046452,
      "cy": 0.041936,
      "rx": 0.0,
      "ry": 0.0,
      "rz": 1.570796,
      "depth_min": 0.001,
      "depth_max": 0.001,
      "contact_frac": 0.086
    },
    {
      "gx": 35,
      "gy": 0,
      "cx": -0.039703,
      "cy": 0.029699,
      "rx": 0.0,
      "ry": 0.0,
      "rz": 1.570796,
      "depth_min": 0.001,
      "depth_max": 0.001,
      "contact_frac": 0.221
    },
    {
      "gx": 36,
      "gy": 0,
      "cx": -0.045602,
      "cy": 0.032559,
      "rx": 0.0,
      "ry": 0.0,
      "rz": 1.570796,
      "depth_min": 0.001,
      "depth_max": 0.001,
      "contact_frac": 0.066
    },
    {
      "gx": 37,
      "gy": 0,
      "cx": -0.036908,
      "cy": 0.050577,
      "rx": 0.0,
      "ry": 0.0,
      "rz": 1.570796,
      "depth_min": 0.001,
      "depth_max": 0.001,
      "contact_frac": 0.087
    },
    {
      "gx": 38,
      "gy": 0,
      "cx": -0.029544,
      "cy": 0.021837,
      "rx": 0.0,
      "ry": 0.0,
      "rz": 1.570796,
      "depth_min": 0.001,
      "depth_max": 0.001,
      "contact_frac": 0.111
    },
    {
      "gx": 39,
      "gy": 0,
      "cx": -0.036278,
      "cy": 0.023181,
      "rx": 0.0,
      "ry": 0.0,
      "rz": 1.570796,
      "depth_min": 0.001,
      "depth_max": 0.001,
      "contact_frac": 0.102
    },
    {
      "gx": 40,
      "gy": 0,
      "cx": -0.045359,
      "cy": 0.044075,
      "rx": 0.0,
      "ry": 0.0,
      "rz": 1.570796,
      "depth_min": 0.001,
      "depth_max": 0.001,
      "contact_frac": 0.15
    },
    {
      "gx": 41,
      "gy": 0,
      "cx": -0.048595,
      "cy": 0.061261,
      "rx": 0.0,
      "ry": 0.0,
      "rz": 1.570796,
      "depth_min": 0.001,
      "depth_max": 0.001,
      "contact_frac": 0.063
    },
    {
      "gx": 42,
      "gy": 0,
      "cx": -0.046935,
      "cy": 0.04758,
      "rx": 0.0,
      "ry": 0.0,
      "rz": 1.570796,
      "depth_min": 0.001,
      "depth_max": 0.001,
      "contact_frac": 0.131
    },
    {
      "gx": 43,
      "gy": 0,
      "cx": -0.028534,
      "cy": 0.016859,
      "rx": 0.0,
      "ry": 0.0,
      "rz": 1.570796,
      "depth_min": 0.001,
      "depth_max": 0.001,
      "contact_frac": 0.071
    },
    {
      "gx": 44,
      "gy": 0,
      "cx": -0.056483,
      "cy": 0.063242,
      "rx": 0.0,
      "ry": 0.0,
      "rz": 1.570796,
      "depth_min": 0.001,
      "depth_max": 0.001,
      "contact_frac": 0.076
    },
    {
      "gx": 45,
      "gy": 0,
      "cx": -0.03563,
      "cy": 0.02869,
      "rx": 0.0,
      "ry": 0.0,
      "rz": 1.570796,
      "depth_min": 0.001,
      "depth_max": 0.001,
      "contact_frac": 0.202
    },
    {
      "gx": 46,
      "gy": 0,
      "cx": -0.03618,
      "cy": 0.050114,
      "rx": 0.0,
      "ry": 0.0,
      "rz": 1.570796,
      "depth_min": 0.001,
      "depth_max": 0.001,
      "contact_frac": 0.063
    },
    {
      "gx": 47,
      "gy": 0,
      "cx": -0.034777,
      "cy": 0.026226,
      "rx": 0.0,
      "ry": 0.0,
      "rz": 1.570796,
      "depth_min": 0.001,
      "depth_max": 0.001,
      "contact_frac": 0.125
    },
    {
      "gx": 48,
      "gy": 0,
      "cx": -0.056541,
      "cy": 0.066155,
      "rx": 0.0,
      "ry": 0.0,
      "rz": 1.570796,
      "depth_min": 0.001,
      "depth_max": 0.001,
      "contact_frac": 0.062
    },
    {
      "gx": 49,
      "gy": 0,
      "cx": -0.04526,
      "cy": 0.054854,
      "rx": 0.0,
      "ry": 0.0,
      "rz": 1.570796,
      "depth_min": 0.001,
      "depth_max": 0.001,
      "contact_frac": 0.208
    },
    {
      "gx": 50,
      "gy": 0,
      "cx": -0.030888,
      "cy": 0.031664,
      "rx": 0.0,
      "ry": 0.0,
      "rz": 1.570796,
      "depth_min": 0.001,
      "depth_max": 0.001,
      "contact_frac": 0.064
    },
    {
      "gx": 51,
      "gy": 0,
      "cx": -0.044223,
      "cy": 0.051421,
      "rx": 0.0,
      "ry": 0.0,
      "rz": 1.570796,
      "depth_min": 0.001,
      "depth_max": 0.001,
      "contact_frac": 0.279
    },
    {
      "gx": 52,
      "gy": 0,
      "cx": -0.025537,
      "cy": 0.015811,
      "rx": 0.0,
      "ry": 0.0,
      "rz": 1.570796,
      "depth_min": 0.001,
      "depth_max": 0.001,
      "contact_frac": 0.064
    },
    {
      "gx": 53,
      "gy": 0,
      "cx": -0.034154,
      "cy": 0.021954,
      "rx": 0.0,
      "ry": 0.0,
      "rz": 1.570796,
      "depth_min": 0.001,
      "depth_max": 0.001,
      "contact_frac": 0.061
    },
    {
      "gx": 54,
      "gy": 0,
      "cx": -0.043676,
      "cy": 0.068947,
      "rx": 0.0,
      "ry": 0.0,
      "rz": 1.570796,
      "depth_min": 0.001,
      "depth_max": 0.001,
      "contact_frac": 0.061
    },
    {
      "gx": 55,
      "gy": 0,
      "cx": -0.053745,
      "cy": 0.059431,
      "rx": 0.0,
      "ry": 0.0,
      "rz": 1.570796,
      "depth_min": 0.001,
      "depth_max": 0.001,
      "contact_frac": 0.111
    },
    {
      "gx": 56,
      "gy": 0,
      "cx": -0.035283,
      "cy": 0.057143,
      "rx": 0.0,
      "ry": 0.0,
      "rz": 1.570796,
      "depth_min": 0.001,
      "depth_max": 0.001,
      "contact_frac": 0.054
    },
    {
      "gx": 57,
      "gy": 0,
      "cx": -0.04269,
      "cy": 0.020645,
      "rx": 0.0,
      "ry": 0.0,
      "rz": 1.570796,
      "depth_min": 0.001,
      "depth_max": 0.001,
      "contact_frac": 0.1
    },
    {
      "gx": 58,
      "gy": 0,
      "cx": -0.042555,
      "cy": 0.053762,
      "rx": 0.0,
      "ry": 0.0,
      "rz": 1.570796,
      "depth_min": 0.001,
      "depth_max": 0.001,
      "contact_frac": 0.192
    },
    {
      "gx": 59,
      "gy": 0,
      "cx": -0.04544,
      "cy": 0.05974,
      "rx": 0.0,
      "ry": 0.0,
      "rz": 1.570796,
      "depth_min": 0.001,
      "depth_max": 0.001,
      "contact_frac": 0.089
    },
    {
      "gx": 60,
      "gy": 0,
      "cx": -0.040818,
      "cy": 0.065373,
      "rx": 0.0,
      "ry": 0.0,
      "rz": 1.570796,
      "depth_min": 0.001,
      "depth_max": 0.001,
      "contact_frac": 0.089
    },
    {
      "gx": 61,
      "gy": 0,
      "cx": -0.031981,
      "cy": 0.033127,
      "rx": 0.0,
      "ry": 0.0,
      "rz": 1.570796,
      "depth_min": 0.001,
      "depth_max": 0.001,
      "contact_frac": 0.074
    },
    {
      "gx": 62,
      "gy": 0,
      "cx": -0.044227,
      "cy": 0.017585,
      "rx": 0.0,
      "ry": 0.0,
      "rz": 1.570796,
      "depth_min": 0.001,
      "depth_max": 0.001,
      "contact_frac": 0.104
    },
    {
      "gx": 63,
      "gy": 0,
      "cx": -0.040024,
      "cy": 0.055229,
      "rx": 0.0,
      "ry": 0.0,
      "rz": 1.570796,
      "depth_min": 0.001,
      "depth_max": 0.001,
      "contact_frac": 0.101
    },
    {
      "gx": 64,
      "gy": 0,
      "cx": -0.043262,
      "cy": 0.0475,
      "rx": 0.0,
      "ry": 0.0,
      "rz": 1.570796,
      "depth_min": 0.001,
      "depth_max": 0.001,
      "contact_frac": 0.275
    },
    {
      "gx": 65,
      "gy": 0,
      "cx": -0.044143,
      "cy": 0.011216,
      "rx": 0.0,
      "ry": 0.0,
      "rz": 1.570796,
      "depth_min": 0.001,
      "depth_max": 0.001,
      "contact_frac": 0.054
    },
    {
      "gx": 66,
      "gy": 0,
      "cx": -0.042276,
      "cy": 0.036251,
      "rx": 0.0,
      "ry": 0.0,
      "rz": 1.570796,
      "depth_min": 0.001,
      "depth_max": 0.001,
      "contact_frac": 0.139
    },
    {
      "gx": 67,
      "gy": 0,
      "cx": -0.035494,
      "cy": 0.046473,
      "rx": 0.0,
      "ry": 0.0,
      "rz": 1.570796,
      "depth_min": 0.001,
      "depth_max": 0.001,
      "contact_frac": 0.052
    },
    {
      "gx": 68,
      "gy": 0,
      "cx": -0.038501,
      "cy": 0.025302,
      "rx": 0.0,
      "ry": 0.0,
      "rz": 1.570796,
      "depth_min": 0.001,
      "depth_max": 0.001,
      "contact_frac": 0.153
    },
    {
      "gx": 69,
      "gy": 0,
      "cx": -0.039268,
      "cy": 0.043698,
      "rx": 0.0,
      "ry": 0.0,
      "rz": 1.570796,
      "depth_min": 0.001,
      "depth_max": 0.001,
      "contact_frac": 0.147
    },
    {
      "gx": 70,
      "gy": 0,
      "cx": -0.026447,
      "cy": 0.014483,
      "rx": 0.0,
      "ry": 0.0,
      "rz": 1.570796,
      "depth_min": 0.001,
      "depth_max": 0.001,
      "contact_frac": 0.051
    },
    {
      "gx": 71,
      "gy": 0,
      "cx": -0.039678,
      "cy": 0.022609,
      "rx": 0.0,
      "ry": 0.0,
      "rz": 1.570796,
      "depth_min": 0.001,
      "depth_max": 0.001,
      "contact_frac": 0.103
    },
    {
      "gx": 72,
      "gy": 0,
      "cx": -0.045219,
      "cy": 0.015154,
      "rx": 0.0,
      "ry": 0.0,
      "rz": 1.570796,
      "depth_min": 0.001,
      "depth_max": 0.001,
      "contact_frac": 0.068
    },
    {
      "gx": 73,
      "gy": 0,
      "cx": -0.038002,
      "cy": 0.034864,
      "rx": 0.0,
      "ry": 0.0,
      "rz": 1.570796,
      "depth_min": 0.001,
      "depth_max": 0.001,
      "contact_frac": 0.247
    },
    {
      "gx": 74,
      "gy": 0,
      "cx": -0.034612,
      "cy": 0.038734,
      "rx": 0.0,
      "ry": 0.0,
      "rz": 1.570796,
      "depth_min": 0.001,
      "depth_max": 0.001,
      "contact_frac": 0.059
    },
    {
      "gx": 75,
      "gy": 0,
      "cx": -0.037109,
      "cy": 0.05039,
      "rx": 0.0,
      "ry": 0.0,
      "rz": 1.570796,
      "depth_min": 0.001,
      "depth_max": 0.001,
      "contact_frac": 0.104
    },
    {
      "gx": 76,
      "gy": 0,
      "cx": -0.037682,
      "cy": 0.062483,
      "rx": 0.0,
      "ry": 0.0,
      "rz": 1.570796,
      "depth_min": 0.001,
      "depth_max": 0.001,
      "contact_frac": 0.097
    },
    {
      "gx": 77,
      "gy": 0,
      "cx": -0.039273,
      "cy": 0.044411,
      "rx": 0.0,
      "ry": 0.0,
      "rz": 1.570796,
      "depth_min": 0.001,
      "depth_max": 0.001,
      "contact_frac": 0.144
    },
    {
      "gx": 78,
      "gy": 0,
      "cx": -0.042794,
      "cy": 0.024128,
      "rx": 0.0,
      "ry": 0.0,
      "rz": 1.570796,
      "depth_min": 0.001,
      "depth_max": 0.001,
      "contact_frac": 0.101
    },
    {
      "gx": 79,
      "gy": 0,
      "cx": -0.041394,
      "cy": 0.063892,
      "rx": 0.0,
      "ry": 0.0,
      "rz": 1.570796,
      "depth_min": 0.001,
      "depth_max": 0.001,
      "contact_frac": 0.093
    },
    {
      "gx": 80,
      "gy": 0,
      "cx": -0.046698,
      "cy": 0.047574,
      "rx": 0.0,
      "ry": 0.0,
      "rz": 1.570796,
      "depth_min": 0.001,
      "depth_max": 0.001,
      "contact_frac": 0.146
    },
    {
      "gx": 81,
      "gy": 0,
      "cx": -0.037253,
      "cy": 0.012211,
      "rx": 0.0,
      "ry": 0.0,
      "rz": 1.570796,
      "depth_min": 0.001,
      "depth_max": 0.001,
      "contact_frac": 0.063
    },
    {
      "gx": 82,
      "gy": 0,
      "cx": -0.054707,
      "cy": 0.061752,
      "rx": 0.0,
      "ry": 0.0,
      "rz": 1.570796,
      "depth_min": 0.001,
      "depth_max": 0.001,
      "contact_frac": 0.099
    },
    {
      "gx": 83,
      "gy": 0,
      "cx": -0.045542,
      "cy": 0.03996,
      "rx": 0.0,
      "ry": 0.0,
      "rz": 1.570796,
      "depth_min": 0.001,
      "depth_max": 0.001,
      "contact_frac": 0.087
    },
    {
      "gx": 84,
      "gy": 0,
      "cx": -0.039075,
      "cy": 0.062669,
      "rx": 0.0,
      "ry": 0.0,
      "rz": 1.570796,
      "depth_min": 0.001,
      "depth_max": 0.001,
      "contact_frac": 0.097
    },
    {
      "gx": 85,
      "gy": 0,
      "cx": -0.028115,
      "cy": 0.017979,
      "rx": 0.0,
      "ry": 0.0,
      "rz": 1.570796,
      "depth_min": 0.001,
      "depth_max": 0.001,
      "contact_frac": 0.079
    },
    {
      "gx": 86,
      "gy": 0,
      "cx": -0.041845,
      "cy": 0.043688,
      "rx": 0.0,
      "ry": 0.0,
      "rz": 1.570796,
      "depth_min": 0.001,
      "depth_max": 0.001,
      "contact_frac": 0.221
    },
    {
      "gx": 87,
      "gy": 0,
      "cx": -0.036586,
      "cy": 0.06547,
      "rx": 0.0,
      "ry": 0.0,
      "rz": 1.570796,
      "depth_min": 0.001,
      "depth_max": 0.001,
      "contact_frac": 0.07
    },
    {
      "gx": 88,
      "gy": 0,
      "cx": -0.043736,
      "cy": 0.045644,
      "rx": 0.0,
      "ry": 0.0,
      "rz": 1.570796,
      "depth_min": 0.001,
      "depth_max": 0.001,
      "contact_frac": 0.231
    },
    {
      "gx": 89,
      "gy": 0,
      "cx": -0.036971,
      "cy": 0.053436,
      "rx": 0.0,
      "ry": 0.0,
      "rz": 1.570796,
      "depth_min": 0.001,
      "depth_max": 0.001,
      "contact_frac": 0.093
    },
    {
      "gx": 90,
      "gy": 0,
      "cx": -0.045097,
      "cy": 0.061882,
      "rx": 0.0,
      "ry": 0.0,
      "rz": 1.570796,
      "depth_min": 0.001,
      "depth_max": 0.001,
      "contact_frac": 0.078
    },
    {
      "gx": 91,
      "gy": 0,
      "cx": -0.036922,
      "cy": 0.035796,
      "rx": 0.0,
      "ry": 0.0,
      "rz": 1.570796,
      "depth_min": 0.001,
      "depth_max": 0.001,
      "contact_frac": 0.201
    },
    {
      "gx": 92,
      "gy": 0,
      "cx": -0.034811,
      "cy": 0.025257,
      "rx": 0.0,
      "ry": 0.0,
      "rz": 1.570796,
      "depth_min": 0.001,
      "depth_max": 0.001,
      "contact_frac": 0.108
    },
    {
      "gx": 93,
      "gy": 0,
      "cx": -0.038263,
      "cy": 0.02925,
      "rx": 0.0,
      "ry": 0.0,
      "rz": 1.570796,
      "depth_min": 0.001,
      "depth_max": 0.001,
      "contact_frac": 0.254
    },
    {
      "gx": 94,
      "gy": 0,
      "cx": -0.035147,
      "cy": 0.058772,
      "rx": 0.0,
      "ry": 0.0,
      "rz": 1.570796,
      "depth_min": 0.001,
      "depth_max": 0.001,
      "contact_frac": 0.057
    },
    {
      "gx": 95,
      "gy": 0,
      "cx": -0.039286,
      "cy": 0.069031,
      "rx": 0.0,
      "ry": 0.0,
      "rz": 1.570796,
      "depth_min": 0.001,
      "depth_max": 0.001,
      "contact_frac": 0.058
    },
    {
      "gx": 96,
      "gy": 0,
      "cx": -0.036941,
      "cy": 0.042138,
      "rx": 0.0,
      "ry": 0.0,
      "rz": 1.570796,
      "depth_min": 0.001,
      "depth_max": 0.001,
      "contact_frac": 0.104
    },
    {
      "gx": 97,
      "gy": 0,
      "cx": -0.057083,
      "cy": 0.066115,
      "rx": 0.0,
      "ry": 0.0,
      "rz": 1.570796,
      "depth_min": 0.001,
      "depth_max": 0.001,
      "contact_frac": 0.061
    },
    {
      "gx": 98,
      "gy": 0,
      "cx": -0.040841,
      "cy": 0.047362,
      "rx": 0.0,
      "ry": 0.0,
      "rz": 1.570796,
      "depth_min": 0.001,
      "depth_max": 0.001,
      "contact_frac": 0.173
    },
    {
      "gx": 99,
      "gy": 0,
      "cx": -0.049254,
      "cy": 0.061972,
      "rx": 0.0,
      "ry": 0.0,
      "rz": 1.570796,
      "depth_min": 0.001,
      "depth_max": 0.001,
      "contact_frac": 0.067
    },
    {
      "gx": 100,
      "gy": 0,
      "cx": -0.037313,
      "cy": 0.067907,
      "rx": 0.0,
      "ry": 0.0,
      "rz": 1.570796,
      "depth_min": 0.001,
      "depth_max": 0.001,
      "contact_frac": 0.068
    },
    {
      "gx": 101,
      "gy": 0,
      "cx": -0.04518,
      "cy": 0.012018,
      "rx": 0.0,
      "ry": 0.0,
      "rz": 1.570796,
      "depth_min": 0.001,
      "depth_max": 0.001,
      "contact_frac": 0.053
    },
    {
      "gx": 102,
      "gy": 0,
      "cx": -0.054284,
      "cy": 0.059024,
      "rx": 0.0,
      "ry": 0.0,
      "rz": 1.570796,
      "depth_min": 0.001,
      "depth_max": 0.001,
      "contact_frac": 0.097
    },
    {
      "gx": 103,
      "gy": 0,
      "cx": -0.045549,
      "cy": 0.016287,
      "rx": 0.0,
      "ry": 0.0,
      "rz": 1.570796,
      "depth_min": 0.001,
      "depth_max": 0.001,
      "contact_frac": 0.069
    },
    {
      "gx": 104,
      "gy": 0,
      "cx": -0.042673,
      "cy": 0.046577,
      "rx": 0.0,
      "ry": 0.0,
      "rz": 1.570796,
      "depth_min": 0.001,
      "depth_max": 0.001,
      "contact_frac": 0.27
    },
    {
      "gx": 105,
      "gy": 0,
      "cx": -0.023751,
      "cy": 0.017666,
      "rx": 0.0,
      "ry": 0.0,
      "rz": 1.570796,
      "depth_min": 0.001,
      "depth_max": 0.001,
      "contact_frac": 0.056
    },
    {
      "gx": 106,
      "gy": 0,
      "cx": -0.042202,
      "cy": 0.069963,
      "rx": 0.0,
      "ry": 0.0,
      "rz": 1.570796,
      "depth_min": 0.001,
      "depth_max": 0.001,
      "contact_frac": 0.053
    },
    {
      "gx": 107,
      "gy": 0,
      "cx": -0.047408,
      "cy": 0.051472,
      "rx": 0.0,
      "ry": 0.0,
      "rz": 1.570796,
      "depth_min": 0.001,
      "depth_max": 0.001,
      "contact_frac": 0.139
    },
    {
      "gx": 108,
      "gy": 0,
      "cx": -0.046141,
      "cy": 0.040482,
      "rx": 0.0,
      "ry": 0.0,
      "rz": 1.570796,
      "depth_min": 0.001,
      "depth_max": 0.001,
      "contact_frac": 0.077
    },
    {
      "gx": 109,
      "gy": 0,
      "cx": -0.041603,
      "cy": 0.049371,
      "rx": 0.0,
      "ry": 0.0,
      "rz": 1.570796,
      "depth_min": 0.001,
      "depth_max": 0.001,
      "contact_frac": 0.251
    },
    {
      "gx": 110,
      "gy": 0,
      "cx": -0.033451,
      "cy": 0.037195,
      "rx": 0.0,
      "ry": 0.0,
      "rz": 1.570796,
      "depth_min": 0.001,
      "depth_max": 0.001,
      "contact_frac": 0.053
    },
    {
      "gx": 111,
      "gy": 0,
      "cx": -0.03031,
      "cy": 0.025278,
      "rx": 0.0,
      "ry": 0.0,
      "rz": 1.570796,
      "depth_min": 0.001,
      "depth_max": 0.001,
      "contact_frac": 0.11
    },
    {
      "gx": 112,
      "gy": 0,
      "cx": -0.04844,
      "cy": 0.052884,
      "rx": 0.0,
      "ry": 0.0,
      "rz": 1.570796,
      "depth_min": 0.001,
      "depth_max": 0.001,
      "contact_frac": 0.134
    },
    {
      "gx": 113,
      "gy": 0,
      "cx": -0.036266,
      "cy": 0.052724,
      "rx": 0.0,
      "ry": 0.0,
      "rz": 1.570796,
      "depth_min": 0.001,
      "depth_max": 0.001,
      "contact_frac": 0.062
    },
    {
      "gx": 114,
      "gy": 0,
      "cx": -0.041312,
      "cy": 0.022347,
      "rx": 0.0,
      "ry": 0.0,
      "rz": 1.570796,
      "depth_min": 0.001,
      "depth_max": 0.001,
      "contact_frac": 0.096
    },
    {
      "gx": 115,
      "gy": 0,
      "cx": -0.037009,
      "cy": 0.058043,
      "rx": 0.0,
      "ry": 0.0,
      "rz": 1.570796,
      "depth_min": 0.001,
      "depth_max": 0.001,
      "contact_frac": 0.1
    },
    {
      "gx": 116,
      "gy": 0,
      "cx": -0.040208,
      "cy": 0.033881,
      "rx": 0.0,
      "ry": 0.0,
      "rz": 1.570796,
      "depth_min": 0.001,
      "depth_max": 0.001,
      "contact_frac": 0.261
    },
    {
      "gx": 117,
      "gy": 0,
      "cx": -0.04245,
      "cy": 0.026725,
      "rx": 0.0,
      "ry": 0.0,
      "rz": 1.570796,
      "depth_min": 0.001,
      "depth_max": 0.001,
      "contact_frac": 0.105
    },
    {
      "gx": 118,
      "gy": 0,
      "cx": -0.04117,
      "cy": 0.011502,
      "rx": 0.0,
      "ry": 0.0,
      "rz": 1.570796,
      "depth_min": 0.001,
      "depth_max": 0.001,
      "contact_frac": 0.051
    },
    {
      "gx": 119,
      "gy": 0,
      "cx": -0.044567,
      "cy": 0.062934,
      "rx": 0.0,
      "ry": 0.0,
      "rz": 1.570796,
      "depth_min": 0.001,
      "depth_max": 0.001,
      "contact_frac": 0.083
    },
    {
      "gx": 120,
      "gy": 0,
      "cx": -0.044347,
      "cy": 0.053794,
      "rx": 0.0,
      "ry": 0.0,
      "rz": 1.570796,
      "depth_min": 0.001,
      "depth_max": 0.001,
      "contact_frac": 0.24
    },
    {
      "gx": 121,
      "gy": 0,
      "cx": -0.041688,
      "cy": 0.066102,
      "rx": 0.0,
      "ry": 0.0,
      "rz": 1.570796,
      "depth_min": 0.001,
      "depth_max": 0.001,
      "contact_frac": 0.072
    },
    {
      "gx": 122,
      "gy": 0,
      "cx": -0.053207,
      "cy": 0.061093,
      "rx": 0.0,
      "ry": 0.0,
      "rz": 1.570796,
      "depth_min": 0.001,
      "depth_max": 0.001,
      "contact_frac": 0.113
    },
    {
      "gx": 123,
      "gy": 0,
      "cx": -0.035806,
      "cy": 0.040757,
      "rx": 0.0,
      "ry": 0.0,
      "rz": 1.570796,
      "depth_min": 0.001,
      "depth_max": 0.001,
      "contact_frac": 0.076
    },
    {
      "gx": 124,
      "gy": 0,
      "cx": -0.051424,
      "cy": 0.054122,
      "rx": 0.0,
      "ry": 0.0,
      "rz": 1.570796,
      "depth_min": 0.001,
      "depth_max": 0.001,
      "contact_frac": 0.097
    },
    {
      "gx": 125,
      "gy": 0,
      "cx": -0.037176,
      "cy": 0.025698,
      "rx": 0.0,
      "ry": 0.0,
      "rz": 1.570796,
      "depth_min": 0.001,
      "depth_max": 0.001,
      "contact_frac": 0.191
    },
    {
      "gx": 126,
      "gy": 0,
      "cx": -0.027719,
      "cy": 0.014392,
      "rx": 0.0,
      "ry": 0.0,
      "rz": 1.570796,
      "depth_min": 0.001,
      "depth_max": 0.001,
      "contact_frac": 0.051
    },
    {
      "gx": 127,
      "gy": 0,
      "cx": -0.039241,
      "cy": 0.036545,
      "rx": 0.0,
      "ry": 0.0,
      "rz": 1.570796,
      "depth_min": 0.001,
      "depth_max": 0.001,
      "contact_frac": 0.227
    },
    {
      "gx": 128,
      "gy": 0,
      "cx": -0.042098,
      "cy": 0.068214,
      "rx": 0.0,
      "ry": 0.0,
      "rz": 1.570796,
      "depth_min": 0.001,
      "depth_max": 0.001,
      "contact_frac": 0.062
    },
    {
      "gx": 129,
      "gy": 0,
      "cx": -0.046698,
      "cy": 0.017136,
      "rx": 0.0,
      "ry": 0.0,
      "rz": 1.570796,
      "depth_min": 0.001,
      "depth_max": 0.001,
      "contact_frac": 0.06
    },
    {
      "gx": 130,
      "gy": 0,
      "cx": -0.04139,
      "cy": 0.027882,
      "rx": 0.0,
      "ry": 0.0,
      "rz": 1.570796,
      "depth_min": 0.001,
      "depth_max": 0.001,
      "contact_frac": 0.108
    },
    {
      "gx": 131,
      "gy": 0,
      "cx": -0.037045,
      "cy": 0.018104,
      "rx": 0.0,
      "ry": 0.0,
      "rz": 1.570796,
      "depth_min": 0.001,
      "depth_max": 0.001,
      "contact_frac": 0.081
    },
    {
      "gx": 132,
      "gy": 0,
      "cx": -0.041746,
      "cy": 0.018672,
      "rx": 0.0,
      "ry": 0.0,
      "rz": 1.570796,
      "depth_min": 0.001,
      "depth_max": 0.001,
      "contact_frac": 0.1
    },
    {
      "gx": 133,
      "gy": 0,
      "cx": -0.02332,
      "cy": 0.01748,
      "rx": 0.0,
      "ry": 0.0,
      "rz": 1.570796,
      "depth_min": 0.001,
      "depth_max": 0.001,
      "contact_frac": 0.051
    },
    {
      "gx": 134,
      "gy": 0,
      "cx": -0.02639,
      "cy": 0.014899,
      "rx": 0.0,
      "ry": 0.0,
      "rz": 1.570796,
      "depth_min": 0.001,
      "depth_max": 0.001,
      "contact_frac": 0.053
    },
    {
      "gx": 135,
      "gy": 0,
      "cx": -0.057624,
      "cy": 0.066504,
      "rx": 0.0,
      "ry": 0.0,
      "rz": 1.570796,
      "depth_min": 0.001,
      "depth_max": 0.001,
      "contact_frac": 0.056
    },
    {
      "gx": 136,
      "gy": 0,
      "cx": -0.036013,
      "cy": 0.020988,
      "rx": 0.0,
      "ry": 0.0,
      "rz": 1.570796,
      "depth_min": 0.001,
      "depth_max": 0.001,
      "contact_frac": 0.068
    },
    {
      "gx": 137,
      "gy": 0,
      "cx": -0.042801,
      "cy": 0.059058,
      "rx": 0.0,
      "ry": 0.0,
      "rz": 1.570796,
      "depth_min": 0.001,
      "depth_max": 0.001,
      "contact_frac": 0.103
    },
    {
      "gx": 138,
      "gy": 0,
      "cx": -0.036883,
      "cy": 0.012173,
      "rx": 0.0,
      "ry": 0.0,
      "rz": 1.570796,
      "depth_min": 0.001,
      "depth_max": 0.001,
      "contact_frac": 0.052
    },
    {
      "gx": 139,
      "gy": 0,
      "cx": -0.029261,
      "cy": 0.029162,
      "rx": 0.0,
      "ry": 0.0,
      "rz": 1.570796,
      "depth_min": 0.001,
      "depth_max": 0.001,
      "contact_frac": 0.059
    },
    {
      "gx": 140,
      "gy": 0,
      "cx": -0.036136,
      "cy": 0.042966,
      "rx": 0.0,
      "ry": 0.0,
      "rz": 1.570796,
      "depth_min": 0.001,
      "depth_max": 0.001,
      "contact_frac": 0.061
    },
    {
      "gx": 141,
      "gy": 0,
      "cx": -0.043697,
      "cy": 0.029723,
      "rx": 0.0,
      "ry": 0.0,
      "rz": 1.570796,
      "depth_min": 0.001,
      "depth_max": 0.001,
      "contact_frac": 0.103
    },
    {
      "gx": 142,
      "gy": 0,
      "cx": -0.048797,
      "cy": 0.05887,
      "rx": 0.0,
      "ry": 0.0,
      "rz": 1.570796,
      "depth_min": 0.001,
      "depth_max": 0.001,
      "contact_frac": 0.099
    },
    {
      "gx": 143,
      "gy": 0,
      "cx": -0.038029,
      "cy": 0.060005,
      "rx": 0.0,
      "ry": 0.0,
      "rz": 1.570796,
      "depth_min": 0.001,
      "depth_max": 0.001,
      "contact_frac": 0.093
    },
    {
      "gx": 144,
      "gy": 0,
      "cx": -0.04343,
      "cy": 0.065665,
      "rx": 0.0,
      "ry": 0.0,
      "rz": 1.570796,
      "depth_min": 0.001,
      "depth_max": 0.001,
      "contact_frac": 0.084
    },
    {
      "gx": 145,
      "gy": 0,
      "cx": -0.041607,
      "cy": 0.024131,
      "rx": 0.0,
      "ry": 0.0,
      "rz": 1.570796,
      "depth_min": 0.001,
      "depth_max": 0.001,
      "contact_frac": 0.1
    },
    {
      "gx": 146,
      "gy": 0,
      "cx": -0.04543,
      "cy": 0.027085,
      "rx": 0.0,
      "ry": 0.0,
      "rz": 1.570796,
      "depth_min": 0.001,
      "depth_max": 0.001,
      "contact_frac": 0.077
    },
    {
      "gx": 147,
      "gy": 0,
      "cx": -0.044231,
      "cy": 0.056107,
      "rx": 0.0,
      "ry": 0.0,
      "rz": 1.570796,
      "depth_min": 0.001,
      "depth_max": 0.001,
      "contact_frac": 0.174
    },
    {
      "gx": 148,
      "gy": 0,
      "cx": -0.031462,
      "cy": 0.03098,
      "rx": 0.0,
      "ry": 0.0,
      "rz": 1.570796,
      "depth_min": 0.001,
      "depth_max": 0.001,
      "contact_frac": 0.085
    },
    {
      "gx": 149,
      "gy": 0,
      "cx": -0.029934,
      "cy": 0.020367,
      "rx": 0.0,
      "ry": 0.0,
      "rz": 1.570796,
      "depth_min": 0.001,
      "depth_max": 0.001,
      "contact_frac": 0.115
    },
    {
      "gx": 150,
      "gy": 0,
      "cx": -0.043554,
      "cy": 0.043167,
      "rx": 0.0,
      "ry": 0.0,
      "rz": 1.570796,
      "depth_min": 0.001,
      "depth_max": 0.001,
      "contact_frac": 0.188
    },
    {
      "gx": 151,
      "gy": 0,
      "cx": -0.039084,
      "cy": 0.066622,
      "rx": 0.0,
      "ry": 0.0,
      "rz": 1.570796,
      "depth_min": 0.001,
      "depth_max": 0.001,
      "contact_frac": 0.072
    },
    {
      "gx": 152,
      "gy": 0,
      "cx": -0.032901,
      "cy": 0.024899,
      "rx": 0.0,
      "ry": 0.0,
      "rz": 1.570796,
      "depth_min": 0.001,
      "depth_max": 0.001,
      "contact_frac": 0.113
    },
    {
      "gx": 153,
      "gy": 0,
      "cx": -0.042265,
      "cy": 0.038256,
      "rx": 0.0,
      "ry": 0.0,
      "rz": 1.570796,
      "depth_min": 0.001,
      "depth_max": 0.001,
      "contact_frac": 0.152
    },
    {
      "gx": 154,
      "gy": 0,
      "cx": -0.037392,
      "cy": 0.025667,
      "rx": 0.0,
      "ry": 0.0,
      "rz": 1.570796,
      "depth_min": 0.001,
      "depth_max": 0.001,
      "contact_frac": 0.185
    },
    {
      "gx": 155,
      "gy": 0,
      "cx": -0.040105,
      "cy": 0.016485,
      "rx": 0.0,
      "ry": 0.0,
      "rz": 1.570796,
      "depth_min": 0.001,
      "depth_max": 0.001,
      "contact_frac": 0.098
    },
    {
      "gx": 156,
      "gy": 0,
      "cx": -0.024105,
      "cy": 0.019376,
      "rx": 0.0,
      "ry": 0.0,
      "rz": 1.570796,
      "depth_min": 0.001,
      "depth_max": 0.001,
      "contact_frac": 0.063
    },
    {
      "gx": 157,
      "gy": 0,
      "cx": -0.03938,
      "cy": 0.069877,
      "rx": 0.0,
      "ry": 0.0,
      "rz": 1.570796,
      "depth_min": 0.001,
      "depth_max": 0.001,
      "contact_frac": 0.054
    },
    {
      "gx": 158,
      "gy": 0,
      "cx": -0.04581,
      "cy": 0.027368,
      "rx": 0.0,
      "ry": 0.0,
      "rz": 1.570796,
      "depth_min": 0.001,
      "depth_max": 0.001,
      "contact_frac": 0.061
    },
    {
      "gx": 159,
      "gy": 0,
      "cx": -0.045138,
      "cy": 0.051493,
      "rx": 0.0,
      "ry": 0.0,
      "rz": 1.570796,
      "depth_min": 0.001,
      "depth_max": 0.001,
      "contact_frac": 0.264
    },
    {
      "gx": 160,
      "gy": 0,
      "cx": -0.032221,
      "cy": 0.026169,
      "rx": 0.0,
      "ry": 0.0,
      "rz": 1.570796,
      "depth_min": 0.001,
      "depth_max": 0.001,
      "contact_frac": 0.112
    },
    {
      "gx": 161,
      "gy": 0,
      "cx": -0.050973,
      "cy": 0.055053,
      "rx": 0.0,
      "ry": 0.0,
      "rz": 1.570796,
      "depth_min": 0.001,
      "depth_max": 0.001,
      "contact_frac": 0.105
    },
    {
      "gx": 162,
      "gy": 0,
      "cx": -0.055361,
      "cy": 0.058245,
      "rx": 0.0,
      "ry": 0.0,
      "rz": 1.570796,
      "depth_min": 0.001,
      "depth_max": 0.001,
      "contact_frac": 0.07
    },
    {
      "gx": 163,
      "gy": 0,
      "cx": -0.03462,
      "cy": 0.036441,
      "rx": 0.0,
      "ry": 0.0,
      "rz": 1.570796,
      "depth_min": 0.001,
      "depth_max": 0.001,
      "contact_frac": 0.085
    },
    {
      "gx": 164,
      "gy": 0,
      "cx": -0.042155,
      "cy": 0.049032,
      "rx": 0.0,
      "ry": 0.0,
      "rz": 1.570796,
      "depth_min": 0.001,
      "depth_max": 0.001,
      "contact_frac": 0.268
    },
    {
      "gx": 165,
      "gy": 0,
      "cx": -0.053679,
      "cy": 0.062156,
      "rx": 0.0,
      "ry": 0.0,
      "rz": 1.570796,
      "depth_min": 0.001,
      "depth_max": 0.001,
      "contact_frac": 0.102
    },
    {
      "gx": 166,
      "gy": 0,
      "cx": -0.038123,
      "cy": 0.056198,
      "rx": 0.0,
      "ry": 0.0,
      "rz": 1.570796,
      "depth_min": 0.001,
      "depth_max": 0.001,
      "contact_frac": 0.1
    },
    {
      "gx": 167,
      "gy": 0,
      "cx": -0.037359,
      "cy": 0.013156,
      "rx": 0.0,
      "ry": 0.0,
      "rz": 1.570796,
      "depth_min": 0.001,
      "depth_max": 0.001,
      "contact_frac": 0.066
    },
    {
      "gx": 168,
      "gy": 0,
      "cx": -0.038073,
      "cy": 0.025185,
      "rx": 0.0,
      "ry": 0.0,
      "rz": 1.570796,
      "depth_min": 0.001,
      "depth_max": 0.001,
      "contact_frac": 0.16
    },
    {
      "gx": 169,
      "gy": 0,
      "cx": -0.044809,
      "cy": 0.067419,
      "rx": 0.0,
      "ry": 0.0,
      "rz": 1.570796,
      "depth_min": 0.001,
      "depth_max": 0.001,
      "contact_frac": 0.065
    },
    {
      "gx": 170,
      "gy": 0,
      "cx": -0.043928,
      "cy": 0.041004,
      "rx": 0.0,
      "ry": 0.0,
      "rz": 1.570796,
      "depth_min": 0.001,
      "depth_max": 0.001,
      "contact_frac": 0.151
    },
    {
      "gx": 171,
      "gy": 0,
      "cx": -0.045875,
      "cy": 0.050412,
      "rx": 0.0,
      "ry": 0.0,
      "rz": 1.570796,
      "depth_min": 0.001,
      "depth_max": 0.001,
      "contact_frac": 0.214
    },
    {
      "gx": 172,
      "gy": 0,
      "cx": -0.042399,
      "cy": 0.043449,
      "rx": 0.0,
      "ry": 0.0,
      "rz": 1.570796,
      "depth_min": 0.001,
      "depth_max": 0.001,
      "contact_frac": 0.213
    },
    {
      "gx": 173,
      "gy": 0,
      "cx": -0.042063,
      "cy": 0.05396,
      "rx": 0.0,
      "ry": 0.0,
      "rz": 1.570796,
      "depth_min": 0.001,
      "depth_max": 0.001,
      "contact_frac": 0.177
    },
    {
      "gx": 174,
      "gy": 0,
      "cx": -0.044441,
      "cy": 0.028877,
      "rx": 0.0,
      "ry": 0.0,
      "rz": 1.570796,
      "depth_min": 0.001,
      "depth_max": 0.001,
      "contact_frac": 0.103
    },
    {
      "gx": 175,
      "gy": 0,
      "cx": -0.027455,
      "cy": 0.024473,
      "rx": 0.0,
      "ry": 0.0,
      "rz": 1.570796,
      "depth_min": 0.001,
      "depth_max": 0.001,
      "contact_frac": 0.069
    },
    {
      "gx": 176,
      "gy": 0,
      "cx": -0.036223,
      "cy": 0.051515,
      "rx": 0.0,
      "ry": 0.0,
      "rz": 1.570796,
      "depth_min": 0.001,
      "depth_max": 0.001,
      "contact_frac": 0.061
    },
    {
      "gx": 177,
      "gy": 0,
      "cx": -0.042636,
      "cy": 0.026987,
      "rx": 0.0,
      "ry": 0.0,
      "rz": 1.570796,
      "depth_min": 0.001,
      "depth_max": 0.001,
      "contact_frac": 0.105
    },
    {
      "gx": 178,
      "gy": 0,
      "cx": -0.041422,
      "cy": 0.06094,
      "rx": 0.0,
      "ry": 0.0,
      "rz": 1.570796,
      "depth_min": 0.001,
      "depth_max": 0.001,
      "contact_frac": 0.099
    },
    {
      "gx": 179,
      "gy": 0,
      "cx": -0.047636,
      "cy": 0.04868,
      "rx": 0.0,
      "ry": 0.0,
      "rz": 1.570796,
      "depth_min": 0.001,
      "depth_max": 0.001,
      "contact_frac": 0.121
    },
    {
      "gx": 180,
      "gy": 0,
      "cx": -0.039284,
      "cy": 0.044479,
      "rx": 0.0,
      "ry": 0.0,
      "rz": 1.570796,
      "depth_min": 0.001,
      "depth_max": 0.001,
      "contact_frac": 0.144
    },
    {
      "gx": 181,
      "gy": 0,
      "cx": -0.043169,
      "cy": 0.056095,
      "rx": 0.0,
      "ry": 0.0,
      "rz": 1.570796,
      "depth_min": 0.001,
      "depth_max": 0.001,
      "contact_frac": 0.151
    },
    {
      "gx": 182,
      "gy": 0,
      "cx": -0.029463,
      "cy": 0.020319,
      "rx": 0.0,
      "ry": 0.0,
      "rz": 1.570796,
      "depth_min": 0.001,
      "depth_max": 0.001,
      "contact_frac": 0.114
    },
    {
      "gx": 183,
      "gy": 0,
      "cx": -0.054463,
      "cy": 0.057577,
      "rx": 0.0,
      "ry": 0.0,
      "rz": 1.570796,
      "depth_min": 0.001,
      "depth_max": 0.001,
      "contact_frac": 0.077
    },
    {
      "gx": 184,
      "gy": 0,
      "cx": -0.045469,
      "cy": 0.024506,
      "rx": 0.0,
      "ry": 0.0,
      "rz": 1.570796,
      "depth_min": 0.001,
      "depth_max": 0.001,
      "contact_frac": 0.075
    },
    {
      "gx": 185,
      "gy": 0,
      "cx": -0.052297,
      "cy": 0.062965,
      "rx": 0.0,
      "ry": 0.0,
      "rz": 1.570796,
      "depth_min": 0.001,
      "depth_max": 0.001,
      "contact_frac": 0.095
    },
    {
      "gx": 186,
      "gy": 0,
      "cx": -0.049915,
      "cy": 0.047683,
      "rx": 0.0,
      "ry": 0.0,
      "rz": 1.570796,
      "depth_min": 0.001,
      "depth_max": 0.001,
      "contact_frac": 0.06
    },
    {
      "gx": 187,
      "gy": 0,
      "cx": -0.028945,
      "cy": 0.023316,
      "rx": 0.0,
      "ry": 0.0,
      "rz": 1.570796,
      "depth_min": 0.001,
      "depth_max": 0.001,
      "contact_frac": 0.108
    },
    {
      "gx": 188,
      "gy": 0,
      "cx": -0.03243,
      "cy": 0.018747,
      "rx": 0.0,
      "ry": 0.0,
      "rz": 1.570796,
      "depth_min": 0.001,
      "depth_max": 0.001,
      "contact_frac": 0.053
    },
    {
      "gx": 189,
      "gy": 0,
      "cx": -0.039591,
      "cy": 0.065719,
      "rx": 0.0,
      "ry": 0.0,
      "rz": 1.570796,
      "depth_min": 0.001,
      "depth_max": 0.001,
      "contact_frac": 0.09
    },
    {
      "gx": 190,
      "gy": 0,
      "cx": -0.056534,
      "cy": 0.060561,
      "rx": 0.0,
      "ry": 0.0,
      "rz": 1.570796,
      "depth_min": 0.001,
      "depth_max": 0.001,
      "contact_frac": 0.069
    },
    {
      "gx": 191,
      "gy": 0,
      "cx": -0.046539,
      "cy": 0.053661,
      "rx": 0.0,
      "ry": 0.0,
      "rz": 1.570796,
      "depth_min": 0.001,
      "depth_max": 0.001,
      "contact_frac": 0.188
    },
    {
      "gx": 192,
      "gy": 0,
      "cx": -0.051241,
      "cy": 0.059772,
      "rx": 0.0,
      "ry": 0.0,
      "rz": 1.570796,
      "depth_min": 0.001,
      "depth_max": 0.001,
      "contact_frac": 0.116
    },
    {
      "gx": 193,
      "gy": 0,
      "cx": -0.055335,
      "cy": 0.063457,
      "rx": 0.0,
      "ry": 0.0,
      "rz": 1.570796,
      "depth_min": 0.001,
      "depth_max": 0.001,
      "contact_frac": 0.081
    },
    {
      "gx": 194,
      "gy": 0,
      "cx": -0.035723,
      "cy": 0.021027,
      "rx": 0.0,
      "ry": 0.0,
      "rz": 1.570796,
      "depth_min": 0.001,
      "depth_max": 0.001,
      "contact_frac": 0.066
    },
    {
      "gx": 195,
      "gy": 0,
      "cx": -0.046232,
      "cy": 0.038999,
      "rx": 0.0,
      "ry": 0.0,
      "rz": 1.570796,
      "depth_min": 0.001,
      "depth_max": 0.001,
      "contact_frac": 0.055
    },
    {
      "gx": 196,
      "gy": 0,
      "cx": -0.035645,
      "cy": 0.032668,
      "rx": 0.0,
      "ry": 0.0,
      "rz": 1.570796,
      "depth_min": 0.001,
      "depth_max": 0.001,
      "contact_frac": 0.181
    },
    {
      "gx": 197,
      "gy": 0,
      "cx": -0.044614,
      "cy": 0.021778,
      "rx": 0.0,
      "ry": 0.0,
      "rz": 1.570796,
      "depth_min": 0.001,
      "depth_max": 0.001,
      "contact_frac": 0.098
    },
    {
      "gx": 198,
      "gy": 0,
      "cx": -0.038223,
      "cy": 0.044754,
      "rx": 0.0,
      "ry": 0.0,
      "rz": 1.570796,
      "depth_min": 0.001,
      "depth_max": 0.001,
      "contact_frac": 0.123
    },
    {
      "gx": 199,
      "gy": 0,
      "cx": -0.04309,
      "cy": 0.052667,
      "rx": 0.0,
      "ry": 0.0,
      "rz": 1.570796,
      "depth_min": 0.001,
      "depth_max": 0.001,
      "contact_frac": 0.232
    }
  ],
  "_rotation_name": "+Z up (original) + Z+90\u00b0",
  "_rotation_degrees": [
    0.0,
    0.0,
    90.0
  ],
  "_sensor_length_mm": 5.0,
  "_sensor_step": 0.006,
  "_target_size_mm": 82.0,
  "_grid": "random-200",
  "_overlap_pct": 40.0,
  "_sampling_method": "random",
  "_use_normal_rotation": false
}